{"communityCode":"RULIWEB","timeType":"06H","orderType":"H","articles":[{"order":1,"communityCode":"RULIWEB","bbsId":"300143","articleNo":40458195,"title":"중간에 무슨 일이 있었는지 안봐도 뻔한.manga","writerType":"T","writer":"연유소믈리에","hits":7744,"comments":24,"url":"http://bbs.ruliweb.com/community/board/300143/read/40458195?page=3","writeDt":1545796193000},{"order":2,"communityCode":"RULIWEB","bbsId":"300143","articleNo":40458219,"title":"점술사의 고민.manga","writerType":"T","writer":"시다레호타루","hits":5037,"comments":29,"url":"http://bbs.ruliweb.com/community/board/300143/read/40458219?page=2","writeDt":1545796351000},{"order":3,"communityCode":"RULIWEB","bbsId":"300143","articleNo":40459882,"title":"외주를 막으면 안되는이유","writerType":"T","writer":"愛のfreesia","hits":5032,"comments":35,"url":"http://bbs.ruliweb.com/community/board/300143/read/40459882?page=3","writeDt":1545806166000},{"order":4,"communityCode":"RULIWEB","bbsId":"300143","articleNo":40459870,"title":"CGV 곰표 포대 팝콘 실사.jpg","writerType":"T","writer":"Emrakul","hits":4096,"comments":28,"url":"http://bbs.ruliweb.com/community/board/300143/read/40459870?page=3","writeDt":1545806089000},{"order":5,"communityCode":"RULIWEB","bbsId":"300143","articleNo":40457466,"title":"전남친 후회하게 할려고 살뺐는데..pann","writerType":"T","writer":"부들부들™","hits":3456,"comments":10,"url":"http://bbs.ruliweb.com/community/board/300143/read/40457466?page=3","writeDt":1545791555000},{"order":6,"communityCode":"RULIWEB","bbsId":"300143","articleNo":40460648,"title":"10살차이 나는 고모가 유혹하는 만화 ^,^","writerType":"T","writer":"샤스르리에어","hits":3005,"comments":17,"url":"http://bbs.ruliweb.com/community/board/300143/read/40460648?page=3","writeDt":1545810534000},{"order":7,"communityCode":"RULIWEB","bbsId":"300143","articleNo":40459183,"title":"500 칼로리 vs 500 칼로리 .jpg","writerType":"T","writer":"하루 에스티아","hits":2651,"comments":27,"url":"http://bbs.ruliweb.com/community/board/300143/read/40459183?page=2","writeDt":1545802145000},{"order":8,"communityCode":"RULIWEB","bbsId":"300143","articleNo":40459249,"title":"현재 DC 상태.gif","writerType":"T","writer":"O점","hits":2504,"comments":19,"url":"http://bbs.ruliweb.com/community/board/300143/read/40459249?page=3","writeDt":1545802490000},{"order":9,"communityCode":"RULIWEB","bbsId":"300143","articleNo":40460437,"title":"윤창호법 근황.jpg","writerType":"T","writer":"유게는정말최고야","hits":2419,"comments":20,"url":"http://bbs.ruliweb.com/community/board/300143/read/40460437?page=3","writeDt":1545809345000},{"order":10,"communityCode":"RULIWEB","bbsId":"300143","articleNo":40458971,"title":"여고생 팬티 찍는 방법.gif","writerType":"T","writer":"어그로입니다","hits":2272,"comments":17,"url":"http://bbs.ruliweb.com/community/board/300143/read/40458971?page=3","writeDt":1545800794000},{"order":11,"communityCode":"RULIWEB","bbsId":"300143","articleNo":40459485,"title":"조조의 절약정신.gif","writerType":"T","writer":"가나쵸코","hits":2169,"comments":18,"url":"http://bbs.ruliweb.com/community/board/300143/read/40459485?page=3","writeDt":1545803944000},{"order":12,"communityCode":"RULIWEB","bbsId":"300143","articleNo":40458230,"title":"붕괴 콜라보 광고 수준","writerType":"T","writer":"kla114","hits":2095,"comments":10,"url":"http://bbs.ruliweb.com/community/board/300143/read/40458230?page=2","writeDt":1545796414000},{"order":13,"communityCode":"RULIWEB","bbsId":"300143","articleNo":40458479,"title":"대만 근황.news","writerType":"T","writer":"대동강","hits":1982,"comments":14,"url":"http://bbs.ruliweb.com/community/board/300143/read/40458479?page=3","writeDt":1545797960000},{"order":14,"communityCode":"RULIWEB","bbsId":"300143","articleNo":40458507,"title":"유행 지나간 그 캐릭터 그려봤으요.jpg","writerType":"T","writer":"응엉응엉엉","hits":1933,"comments":12,"url":"http://bbs.ruliweb.com/community/board/300143/read/40458507?page=2","writeDt":1545798104000},{"order":15,"communityCode":"RULIWEB","bbsId":"300143","articleNo":40459863,"title":"전세계로 퍼져나가는 레볼루숑","writerType":"T","writer":"대동강","hits":1910,"comments":9,"url":"http://bbs.ruliweb.com/community/board/300143/read/40459863?page=3","writeDt":1545806037000},{"order":16,"communityCode":"RULIWEB","bbsId":"300143","articleNo":40460674,"title":"중국과 맞먹는 한국의 거지근성....의 진실.jpg","writerType":"T","writer":"부들부들™","hits":1776,"comments":16,"url":"http://bbs.ruliweb.com/community/board/300143/read/40460674?page=2","writeDt":1545810692000},{"order":17,"communityCode":"RULIWEB","bbsId":"300143","articleNo":40457271,"title":"토르와 슈퍼맨 연출 비교.gif","writerType":"T","writer":"쾌청상승","hits":1678,"comments":13,"url":"http://bbs.ruliweb.com/community/board/300143/read/40457271?page=3","writeDt":1545790330000},{"order":18,"communityCode":"RULIWEB","bbsId":"300143","articleNo":40459881,"title":"핀터레스트 공감 甲","writerType":"T","writer":"Cortana","hits":1565,"comments":16,"url":"http://bbs.ruliweb.com/community/board/300143/read/40459881?page=3","writeDt":1545806148000},{"order":19,"communityCode":"RULIWEB","bbsId":"300143","articleNo":40459612,"title":"최면물 대꼴 전개","writerType":"T","writer":"풀빵이","hits":1539,"comments":4,"url":"http://bbs.ruliweb.com/community/board/300143/read/40459612?page=3","writeDt":1545804630000},{"order":20,"communityCode":"RULIWEB","bbsId":"300143","articleNo":40460666,"title":"여기 누르면 중국인이 한 명 사라지는 버튼이","writerType":"T","writer":"여장어그로 빌런","hits":1485,"comments":21,"url":"http://bbs.ruliweb.com/community/board/300143/read/40460666?page=2","writeDt":1545810636000},{"order":21,"communityCode":"RULIWEB","bbsId":"300143","articleNo":40459879,"title":"여법 5번째 전직이 버퍼란 소식을 들은 던파유저","writerType":"T","writer":"빨강머릿","hits":1319,"comments":13,"url":"http://bbs.ruliweb.com/community/board/300143/read/40459879?page=3","writeDt":1545806134000},{"order":22,"communityCode":"RULIWEB","bbsId":"300143","articleNo":40460350,"title":"대머리가 신기한 고양이","writerType":"T","writer":"리링냥","hits":1212,"comments":9,"url":"http://bbs.ruliweb.com/community/board/300143/read/40460350?page=2","writeDt":1545808801000},{"order":23,"communityCode":"RULIWEB","bbsId":"300143","articleNo":40460125,"title":"오뚜기 신제품 근황","writerType":"T","writer":"Redmario","hits":1187,"comments":13,"url":"http://bbs.ruliweb.com/community/board/300143/read/40460125?page=2","writeDt":1545807606000},{"order":24,"communityCode":"RULIWEB","bbsId":"300143","articleNo":40459802,"title":"무서운 싸패 조조.jpg","writerType":"T","writer":"가나쵸코","hits":1128,"comments":8,"url":"http://bbs.ruliweb.com/community/board/300143/read/40459802?page=2","writeDt":1545805644000},{"order":25,"communityCode":"RULIWEB","bbsId":"300143","articleNo":40460132,"title":"3년이 지나서야 단행본이 나온 '뷰티풀 군바리' 웹툰.jpg","writerType":"T","writer":"라시현","hits":974,"comments":8,"url":"http://bbs.ruliweb.com/community/board/300143/read/40460132?page=2","writeDt":1545807666000},{"order":26,"communityCode":"RULIWEB","bbsId":"300143","articleNo":40458817,"title":"일주일 뒤면 나온지 28년 된 영화 명장면 .jpg","writerType":"T","writer":"하루 에스티아","hits":968,"comments":9,"url":"http://bbs.ruliweb.com/community/board/300143/read/40458817?page=2","writeDt":1545799856000},{"order":27,"communityCode":"RULIWEB","bbsId":"300143","articleNo":40458985,"title":"갓뚜기 신제품 근황.jpg","writerType":"T","writer":"룺릾웺","hits":925,"comments":12,"url":"http://bbs.ruliweb.com/community/board/300143/read/40458985?page=2","writeDt":1545800873000},{"order":28,"communityCode":"RULIWEB","bbsId":"300143","articleNo":40458178,"title":"대 vs 소.jpg","writerType":"T","writer":"됐거든?","hits":913,"comments":5,"url":"http://bbs.ruliweb.com/community/board/300143/read/40458178?page=3","writeDt":1545796100000},{"order":29,"communityCode":"RULIWEB","bbsId":"300143","articleNo":40458698,"title":"LG전자 채신근황 캡슐","writerType":"T","writer":"아마다 코코로","hits":880,"comments":19,"url":"http://bbs.ruliweb.com/community/board/300143/read/40458698?page=2","writeDt":1545799148000},{"order":30,"communityCode":"RULIWEB","bbsId":"300143","articleNo":40457484,"title":"국적불명의 음식점.jpg","writerType":"T","writer":"부들부들™","hits":820,"comments":13,"url":"http://bbs.ruliweb.com/community/board/300143/read/40457484?page=2","writeDt":1545791670000},{"order":31,"communityCode":"RULIWEB","bbsId":"300143","articleNo":40459748,"title":"딜ㄷ도의 마음.manga","writerType":"T","writer":"연유소믈리에","hits":814,"comments":10,"url":"http://bbs.ruliweb.com/community/board/300143/read/40459748?page=2","writeDt":1545805317000},{"order":32,"communityCode":"RULIWEB","bbsId":"300143","articleNo":40459413,"title":"CGV 근황.jpg","writerType":"T","writer":"됐거든?","hits":813,"comments":18,"url":"http://bbs.ruliweb.com/community/board/300143/read/40459413?page=1","writeDt":1545803498000},{"order":33,"communityCode":"RULIWEB","bbsId":"300143","articleNo":40458827,"title":"요즘 예능찍고 있는 일본정부.txt","writerType":"T","writer":"아리아발레","hits":777,"comments":11,"url":"http://bbs.ruliweb.com/community/board/300143/read/40458827?page=1","writeDt":1545799935000},{"order":34,"communityCode":"RULIWEB","bbsId":"300143","articleNo":40460636,"title":"(펌)아들에게 차마 못할짓을 한 아버지","writerType":"T","writer":"잠탱이.","hits":763,"comments":7,"url":"http://bbs.ruliweb.com/community/board/300143/read/40460636?page=3","writeDt":1545810471000},{"order":35,"communityCode":"RULIWEB","bbsId":"300143","articleNo":40457233,"title":"알바녀보려고 줄서서 간다는 편의점","writerType":"T","writer":"error37","hits":748,"comments":5,"url":"http://bbs.ruliweb.com/community/board/300143/read/40457233?page=1","writeDt":1545790012000},{"order":36,"communityCode":"RULIWEB","bbsId":"300143","articleNo":40458248,"title":"대륙의 척추 교정법.gif","writerType":"T","writer":"고라파덕™","hits":745,"comments":12,"url":"http://bbs.ruliweb.com/community/board/300143/read/40458248?page=1","writeDt":1545796528000},{"order":37,"communityCode":"RULIWEB","bbsId":"300143","articleNo":40457643,"title":"섹시 보이스에 가버리는 여고생들.manga","writerType":"T","writer":"식봉식봉이","hits":742,"comments":2,"url":"http://bbs.ruliweb.com/community/board/300143/read/40457643?page=3","writeDt":1545792659000},{"order":38,"communityCode":"RULIWEB","bbsId":"300143","articleNo":40459290,"title":"논O비요리","writerType":"T","writer":"망고치즈국밥","hits":738,"comments":15,"url":"http://bbs.ruliweb.com/community/board/300143/read/40459290?page=2","writeDt":1545802740000},{"order":39,"communityCode":"RULIWEB","bbsId":"300143","articleNo":40459021,"title":"예쁘지 않다는 유튜버의 팬아트.jpg","writerType":"T","writer":"ventriloquism","hits":714,"comments":7,"url":"http://bbs.ruliweb.com/community/board/300143/read/40459021?page=1","writeDt":1545801110000},{"order":40,"communityCode":"RULIWEB","bbsId":"300143","articleNo":40457729,"title":"일본 출근길 지하철 근황","writerType":"T","writer":"안경선생","hits":707,"comments":13,"url":"http://bbs.ruliweb.com/community/board/300143/read/40457729?page=3","writeDt":1545793262000},{"order":41,"communityCode":"RULIWEB","bbsId":"300143","articleNo":40459286,"title":"1986년도 성교육 책.jpg","writerType":"T","writer":"흥두루미","hits":696,"comments":8,"url":"http://bbs.ruliweb.com/community/board/300143/read/40459286?page=2","writeDt":1545802713000},{"order":42,"communityCode":"RULIWEB","bbsId":"300143","articleNo":40457636,"title":"우리나라 100명 미만의 희귀 성씨.jpg","writerType":"T","writer":"안경선생","hits":687,"comments":19,"url":"http://bbs.ruliweb.com/community/board/300143/read/40457636?page=3","writeDt":1545792630000},{"order":43,"communityCode":"RULIWEB","bbsId":"300143","articleNo":40457665,"title":"옷 안이 훤히 보이는 여고생.jpg","writerType":"T","writer":"식봉식봉이","hits":673,"comments":8,"url":"http://bbs.ruliweb.com/community/board/300143/read/40457665?page=2","writeDt":1545792862000},{"order":44,"communityCode":"RULIWEB","bbsId":"300143","articleNo":40459163,"title":"넷플릭스 번역 웃기네 ㅋㅋ","writerType":"T","writer":"☆THE TOP☆","hits":665,"comments":4,"url":"http://bbs.ruliweb.com/community/board/300143/read/40459163?page=3","writeDt":1545802024000},{"order":45,"communityCode":"RULIWEB","bbsId":"300143","articleNo":40458469,"title":"아프리카의 묘한 벌칙","writerType":"T","writer":"루리웹-5457059761","hits":663,"comments":9,"url":"http://bbs.ruliweb.com/community/board/300143/read/40458469?page=3","writeDt":1545797890000},{"order":46,"communityCode":"RULIWEB","bbsId":"300143","articleNo":40459495,"title":"저의 가슴이 어떻다고요?","writerType":"T","writer":"오르피아 똥꼬냄새","hits":663,"comments":9,"url":"http://bbs.ruliweb.com/community/board/300143/read/40459495?page=2","writeDt":1545803988000},{"order":47,"communityCode":"RULIWEB","bbsId":"300143","articleNo":40458533,"title":"후방]이쁜척하는 서양여자","writerType":"T","writer":"루리웹-5457059761","hits":658,"comments":12,"url":"http://bbs.ruliweb.com/community/board/300143/read/40458533?page=1","writeDt":1545798255000},{"order":48,"communityCode":"RULIWEB","bbsId":"300143","articleNo":40459415,"title":"최면물 쩡 대꼴 클리셰 . gif","writerType":"T","writer":"마가린","hits":657,"comments":3,"url":"http://bbs.ruliweb.com/community/board/300143/read/40459415?page=1","writeDt":1545803509000},{"order":49,"communityCode":"RULIWEB","bbsId":"300143","articleNo":40460307,"title":"순하게 생긴 사람을 건들면 안되는 이유","writerType":"T","writer":"험버트험버트","hits":645,"comments":7,"url":"http://bbs.ruliweb.com/community/board/300143/read/40460307?page=3","writeDt":1545808583000},{"order":50,"communityCode":"RULIWEB","bbsId":"300143","articleNo":40459276,"title":"아무리 노를 써도 ㅇㅂ의혹을 받지않는 연예인","writerType":"T","writer":"사진이사진읠픽쳐","hits":640,"comments":9,"url":"http://bbs.ruliweb.com/community/board/300143/read/40459276?page=2","writeDt":1545802644000},{"order":51,"communityCode":"RULIWEB","bbsId":"300143","articleNo":40459281,"title":"히토미 테스트","writerType":"T","writer":"4701778","hits":631,"comments":13,"url":"http://bbs.ruliweb.com/community/board/300143/read/40459281?page=2","writeDt":1545802677000},{"order":52,"communityCode":"RULIWEB","bbsId":"300143","articleNo":40459166,"title":"어른스럽게 말해야지!","writerType":"T","writer":"라그나로쓰구이","hits":624,"comments":8,"url":"http://bbs.ruliweb.com/community/board/300143/read/40459166?page=3","writeDt":1545802050000},{"order":53,"communityCode":"RULIWEB","bbsId":"300143","articleNo":40458474,"title":"괴도ㅈㅈ는 동정을 뭐로 땠나여?","writerType":"T","writer":"kla114","hits":624,"comments":6,"url":"http://bbs.ruliweb.com/community/board/300143/read/40458474?page=3","writeDt":1545797921000},{"order":54,"communityCode":"RULIWEB","bbsId":"300143","articleNo":40457648,"title":"베트남 흔한 여자들","writerType":"T","writer":"루리웹-5457059761","hits":622,"comments":3,"url":"http://bbs.ruliweb.com/community/board/300143/read/40457648?page=3","writeDt":1545792720000},{"order":55,"communityCode":"RULIWEB","bbsId":"300143","articleNo":40460105,"title":"이수역 경찰조사결과 전말이 서서히 뜨네","writerType":"T","writer":"루리웹-1025419768","hits":616,"comments":13,"url":"http://bbs.ruliweb.com/community/board/300143/read/40460105?page=3","writeDt":1545807489000},{"order":56,"communityCode":"RULIWEB","bbsId":"300143","articleNo":40458965,"title":"일본인 선호도 1위 의사.gif","writerType":"T","writer":"샤이중도","hits":611,"comments":8,"url":"http://bbs.ruliweb.com/community/board/300143/read/40458965?page=3","writeDt":1545800769000},{"order":57,"communityCode":"RULIWEB","bbsId":"300143","articleNo":40458823,"title":"뇌강.간.gif","writerType":"T","writer":"케이지","hits":610,"comments":3,"url":"http://bbs.ruliweb.com/community/board/300143/read/40458823?page=2","writeDt":1545799895000},{"order":58,"communityCode":"RULIWEB","bbsId":"300143","articleNo":40457801,"title":"히로아카 작가의 가장 큰 실수.jpg","writerType":"T","writer":"식봉식봉이","hits":610,"comments":8,"url":"http://bbs.ruliweb.com/community/board/300143/read/40457801?page=3","writeDt":1545793837000},{"order":59,"communityCode":"RULIWEB","bbsId":"300143","articleNo":40460343,"title":"최근 스트리머 발언 논란","writerType":"T","writer":"변변한남자","hits":607,"comments":8,"url":"http://bbs.ruliweb.com/community/board/300143/read/40460343?page=2","writeDt":1545808764000},{"order":60,"communityCode":"RULIWEB","bbsId":"300143","articleNo":40458669,"title":"여자가 쌩얼로 남친 만나는 만화 ^,^","writerType":"T","writer":"샤스르리에어","hits":607,"comments":8,"url":"http://bbs.ruliweb.com/community/board/300143/read/40458669?page=3","writeDt":1545799002000},{"order":61,"communityCode":"RULIWEB","bbsId":"300143","articleNo":40457758,"title":"과학부로 입부하는.manga","writerType":"T","writer":"빌런냐옹","hits":605,"comments":8,"url":"http://bbs.ruliweb.com/community/board/300143/read/40457758?page=2","writeDt":1545793447000},{"order":62,"communityCode":"RULIWEB","bbsId":"300143","articleNo":40457283,"title":"아;; 님 왜 딜 안하고 구경만해요;;;","writerType":"T","writer":"쿠르스와로","hits":605,"comments":9,"url":"http://bbs.ruliweb.com/community/board/300143/read/40457283?page=3","writeDt":1545790411000},{"order":63,"communityCode":"RULIWEB","bbsId":"300143","articleNo":40457713,"title":"일본식 부대찌개.jpg","writerType":"T","writer":"유이가하마 유이♡","hits":602,"comments":16,"url":"http://bbs.ruliweb.com/community/board/300143/read/40457713?page=3","writeDt":1545793152000},{"order":64,"communityCode":"RULIWEB","bbsId":"300143","articleNo":40459277,"title":"(혐?)(다급).gif","writerType":"T","writer":"하은선혜","hits":601,"comments":8,"url":"http://bbs.ruliweb.com/community/board/300143/read/40459277?page=2","writeDt":1545802644000},{"order":65,"communityCode":"RULIWEB","bbsId":"300143","articleNo":40460665,"title":"단골손님 쫓아내는 미용실","writerType":"T","writer":"로리16세","hits":600,"comments":8,"url":"http://bbs.ruliweb.com/community/board/300143/read/40460665?page=2","writeDt":1545810623000},{"order":66,"communityCode":"RULIWEB","bbsId":"300143","articleNo":40459992,"title":"법적으로 금지해야 하는 광고","writerType":"T","writer":"AquaStellar","hits":595,"comments":7,"url":"http://bbs.ruliweb.com/community/board/300143/read/40459992?page=3","writeDt":1545806881000},{"order":67,"communityCode":"RULIWEB","bbsId":"300143","articleNo":40459160,"title":"엔딩 복선.jpg","writerType":"T","writer":"얼음少女","hits":588,"comments":13,"url":"http://bbs.ruliweb.com/community/board/300143/read/40459160?page=3","writeDt":1545802000000},{"order":68,"communityCode":"RULIWEB","bbsId":"300143","articleNo":40458871,"title":"(후방)마녀학교에서 렌즈생수하는 만화.lense","writerType":"T","writer":"즈라마루금융","hits":585,"comments":7,"url":"http://bbs.ruliweb.com/community/board/300143/read/40458871?page=3","writeDt":1545800223000},{"order":69,"communityCode":"RULIWEB","bbsId":"300143","articleNo":40460443,"title":"원피스 볼때 ㄹㅇ 똥오줌 지렸던 장면.jpg","writerType":"T","writer":"포근한요리사","hits":582,"comments":13,"url":"http://bbs.ruliweb.com/community/board/300143/read/40460443?page=3","writeDt":1545809382000},{"order":70,"communityCode":"RULIWEB","bbsId":"300143","articleNo":40458890,"title":"여친 인증한다.jpg","writerType":"T","writer":"40776","hits":579,"comments":10,"url":"http://bbs.ruliweb.com/community/board/300143/read/40458890?page=3","writeDt":1545800312000},{"order":71,"communityCode":"RULIWEB","bbsId":"300143","articleNo":40460128,"title":"지하철 대꼴 상황","writerType":"T","writer":"케이지","hits":577,"comments":9,"url":"http://bbs.ruliweb.com/community/board/300143/read/40460128?page=2","writeDt":1545807630000},{"order":72,"communityCode":"RULIWEB","bbsId":"300143","articleNo":40459477,"title":"길거리에 버려진 흔한 쓰레기 .jpg","writerType":"T","writer":"모에칸","hits":572,"comments":11,"url":"http://bbs.ruliweb.com/community/board/300143/read/40459477?page=3","writeDt":1545803893000},{"order":73,"communityCode":"RULIWEB","bbsId":"300143","articleNo":40458214,"title":"여고생과 눈을 마주치다.","writerType":"T","writer":"오르피아 똥꼬냄새","hits":571,"comments":7,"url":"http://bbs.ruliweb.com/community/board/300143/read/40458214?page=2","writeDt":1545796320000},{"order":74,"communityCode":"RULIWEB","bbsId":"300143","articleNo":40459407,"title":"소울워커에서 나름 대성공한 반전 .jpg","writerType":"T","writer":"하루 에스티아","hits":570,"comments":8,"url":"http://bbs.ruliweb.com/community/board/300143/read/40459407?page=1","writeDt":1545803444000},{"order":75,"communityCode":"RULIWEB","bbsId":"300143","articleNo":40458233,"title":"청바지 몸매 호불호.gif","writerType":"T","writer":"러블리즈","hits":570,"comments":2,"url":"http://bbs.ruliweb.com/community/board/300143/read/40458233?page=2","writeDt":1545796437000},{"order":76,"communityCode":"RULIWEB","bbsId":"300143","articleNo":40459263,"title":"30대 이상들이 기억하는 걸그룹 3대 여신","writerType":"T","writer":"루리웹-0697762128","hits":564,"comments":5,"url":"http://bbs.ruliweb.com/community/board/300143/read/40459263?page=3","writeDt":1545802570000},{"order":77,"communityCode":"RULIWEB","bbsId":"300143","articleNo":40457634,"title":"(히로아카)먹은 것의 능력을 쓸 수 있는 남자.manga","writerType":"T","writer":"식봉식봉이","hits":558,"comments":16,"url":"http://bbs.ruliweb.com/community/board/300143/read/40457634?page=3","writeDt":1545792623000},{"order":78,"communityCode":"RULIWEB","bbsId":"300143","articleNo":40460331,"title":"아티스 만화 신발 레전드.jpg","writerType":"T","writer":"순규앓이","hits":557,"comments":10,"url":"http://bbs.ruliweb.com/community/board/300143/read/40460331?page=2","writeDt":1545808698000},{"order":79,"communityCode":"RULIWEB","bbsId":"300143","articleNo":40459720,"title":"송하나랑 결혼한썰","writerType":"T","writer":"메루루앀","hits":556,"comments":6,"url":"http://bbs.ruliweb.com/community/board/300143/read/40459720?page=3","writeDt":1545805187000},{"order":80,"communityCode":"RULIWEB","bbsId":"300143","articleNo":40460566,"title":"원피스 처맞기 신.jpg","writerType":"T","writer":"포근한요리사","hits":555,"comments":10,"url":"http://bbs.ruliweb.com/community/board/300143/read/40460566?page=2","writeDt":1545810092000},{"order":81,"communityCode":"RULIWEB","bbsId":"300143","articleNo":40457929,"title":"허리 다친 엄마 배빵때리는 패륜아.jpg","writerType":"T","writer":"Annie♡Tieebers","hits":553,"comments":8,"url":"http://bbs.ruliweb.com/community/board/300143/read/40457929?page=2","writeDt":1545794674000},{"order":82,"communityCode":"RULIWEB","bbsId":"300143","articleNo":40459867,"title":"일베근황","writerType":"T","writer":"저스트히릿","hits":550,"comments":3,"url":"http://bbs.ruliweb.com/community/board/300143/read/40459867?page=3","writeDt":1545806078000},{"order":83,"communityCode":"RULIWEB","bbsId":"300143","articleNo":40459251,"title":"초능력의 3가지 금기사항","writerType":"T","writer":"놀러갈께","hits":550,"comments":5,"url":"http://bbs.ruliweb.com/community/board/300143/read/40459251?page=3","writeDt":1545802499000},{"order":84,"communityCode":"RULIWEB","bbsId":"300143","articleNo":40459083,"title":"직업은 한의사…","writerType":"T","writer":"쯔위입니다","hits":548,"comments":3,"url":"http://bbs.ruliweb.com/community/board/300143/read/40459083?page=2","writeDt":1545801511000},{"order":85,"communityCode":"RULIWEB","bbsId":"300143","articleNo":40460015,"title":"독일 뮤직뱅크 BTS 팬 소녀.gif","writerType":"T","writer":"포도주스","hits":548,"comments":3,"url":"http://bbs.ruliweb.com/community/board/300143/read/40460015?page=2","writeDt":1545806995000},{"order":86,"communityCode":"RULIWEB","bbsId":"300143","articleNo":40459119,"title":"두발 자유화 근황","writerType":"T","writer":"시리아나","hits":546,"comments":13,"url":"http://bbs.ruliweb.com/community/board/300143/read/40459119?page=1","writeDt":1545801748000},{"order":87,"communityCode":"RULIWEB","bbsId":"300143","articleNo":40460625,"title":"원피스에서 고무가 번개를 이기는 이유","writerType":"T","writer":"분위기전환빌런","hits":544,"comments":7,"url":"http://bbs.ruliweb.com/community/board/300143/read/40460625?page=3","writeDt":1545810390000},{"order":88,"communityCode":"RULIWEB","bbsId":"300143","articleNo":40460649,"title":"요즘 애들은 모르는 단체 생활.jpg","writerType":"T","writer":"안경선생","hits":543,"comments":13,"url":"http://bbs.ruliweb.com/community/board/300143/read/40460649?page=3","writeDt":1545810548000},{"order":89,"communityCode":"RULIWEB","bbsId":"300143","articleNo":40458466,"title":"실시간 침착맨ㅋㅋㅋㅋㅋㅋㅋㅋ","writerType":"T","writer":"심슨o","hits":543,"comments":6,"url":"http://bbs.ruliweb.com/community/board/300143/read/40458466?page=3","writeDt":1545797881000},{"order":90,"communityCode":"RULIWEB","bbsId":"300143","articleNo":40457667,"title":"이거 알면 최소 30대","writerType":"T","writer":"부들부들™","hits":542,"comments":12,"url":"http://bbs.ruliweb.com/community/board/300143/read/40457667?page=2","writeDt":1545792881000},{"order":91,"communityCode":"RULIWEB","bbsId":"300143","articleNo":40457802,"title":"너무나도 끔찍한 지뢰 폭발","writerType":"T","writer":"삼지광","hits":538,"comments":6,"url":"http://bbs.ruliweb.com/community/board/300143/read/40457802?page=3","writeDt":1545793839000},{"order":92,"communityCode":"RULIWEB","bbsId":"300143","articleNo":40457631,"title":"일밍아웃하는 작가들","writerType":"T","writer":"유우키 아오이","hits":535,"comments":6,"url":"http://bbs.ruliweb.com/community/board/300143/read/40457631?page=3","writeDt":1545792607000},{"order":93,"communityCode":"RULIWEB","bbsId":"300143","articleNo":40459280,"title":"포켓몬 하렘.jpg","writerType":"T","writer":"Flaky","hits":534,"comments":7,"url":"http://bbs.ruliweb.com/community/board/300143/read/40459280?page=2","writeDt":1545802661000},{"order":94,"communityCode":"RULIWEB","bbsId":"300143","articleNo":40460112,"title":"PC방 판매전략 갑","writerType":"T","writer":"쯔위입니다","hits":534,"comments":5,"url":"http://bbs.ruliweb.com/community/board/300143/read/40460112?page=3","writeDt":1545807550000},{"order":95,"communityCode":"RULIWEB","bbsId":"300143","articleNo":40460455,"title":"난민 과거 ㅋㅋㅋㅋㅋ","writerType":"T","writer":"아재~","hits":534,"comments":6,"url":"http://bbs.ruliweb.com/community/board/300143/read/40460455?page=2","writeDt":1545809443000},{"order":96,"communityCode":"RULIWEB","bbsId":"300143","articleNo":40458781,"title":"취미로 바이크를 타는 여성이다.gif","writerType":"T","writer":"人生無想","hits":533,"comments":5,"url":"http://bbs.ruliweb.com/community/board/300143/read/40458781?page=3","writeDt":1545799644000},{"order":97,"communityCode":"RULIWEB","bbsId":"300143","articleNo":40460365,"title":"ㄹㅇ사황해도 손색없었던 수준의 자연계.jpg","writerType":"T","writer":"포근한요리사","hits":531,"comments":19,"url":"http://bbs.ruliweb.com/community/board/300143/read/40460365?page=1","writeDt":1545808890000},{"order":98,"communityCode":"RULIWEB","bbsId":"300143","articleNo":40457747,"title":"배스트에 올라온 ‘북유럽풍 일본 가정식’ 가게 사진.jpg","writerType":"T","writer":"유이가하마 유이♡","hits":530,"comments":10,"url":"http://bbs.ruliweb.com/community/board/300143/read/40457747?page=2","writeDt":1545793392000},{"order":99,"communityCode":"RULIWEB","bbsId":"300143","articleNo":40459884,"title":"공포의 근손실.jpg","writerType":"T","writer":"로제마인™","hits":529,"comments":5,"url":"http://bbs.ruliweb.com/community/board/300143/read/40459884?page=3","writeDt":1545806217000},{"order":100,"communityCode":"RULIWEB","bbsId":"300143","articleNo":40457816,"title":"구라 같지만 진짜인 위험한 행동.jpg","writerType":"T","writer":"無風地帶™","hits":525,"comments":4,"url":"http://bbs.ruliweb.com/community/board/300143/read/40457816?page=2","writeDt":1545793960000},{"order":101,"communityCode":"RULIWEB","bbsId":"300143","articleNo":40457760,"title":"옛날 상류층 사이에서는 동성애가 유행했으며.manga","writerType":"T","writer":"식봉식봉이","hits":523,"comments":2,"url":"http://bbs.ruliweb.com/community/board/300143/read/40457760?page=1","writeDt":1545793483000},{"order":102,"communityCode":"RULIWEB","bbsId":"300143","articleNo":40457657,"title":"소방관: 아니, 씨빨, 지금 불 났다고요!!!","writerType":"T","writer":"달빛물든","hits":521,"comments":4,"url":"http://bbs.ruliweb.com/community/board/300143/read/40457657?page=2","writeDt":1545792802000},{"order":103,"communityCode":"RULIWEB","bbsId":"300143","articleNo":40458657,"title":"구세군 자선냄비 내 기부금 어디에 쓰는지 몰라 찬바람","writerType":"T","writer":"아사히 슈퍼드라이","hits":517,"comments":14,"url":"http://bbs.ruliweb.com/community/board/300143/read/40458657?page=3","writeDt":1545798947000},{"order":104,"communityCode":"RULIWEB","bbsId":"300143","articleNo":40459315,"title":"서울에 30도 지진","writerType":"T","writer":"쯔위입니다","hits":515,"comments":15,"url":"http://bbs.ruliweb.com/community/board/300143/read/40459315?page=1","writeDt":1545802907000},{"order":105,"communityCode":"RULIWEB","bbsId":"300143","articleNo":40460118,"title":"하루 12시간씩 일하고 회식 참석하기 싫었던 신입사원.jpg","writerType":"T","writer":"부들부들™","hits":513,"comments":5,"url":"http://bbs.ruliweb.com/community/board/300143/read/40460118?page=2","writeDt":1545807568000},{"order":106,"communityCode":"RULIWEB","bbsId":"300143","articleNo":40459904,"title":"한입만 먹어도 배부른 빵","writerType":"T","writer":"JupiTer☆","hits":513,"comments":5,"url":"http://bbs.ruliweb.com/community/board/300143/read/40459904?page=2","writeDt":1545806348000},{"order":107,"communityCode":"RULIWEB","bbsId":"300143","articleNo":40460119,"title":"실제로 존재하는 슈퍼솔져","writerType":"T","writer":"루리웹-6180343270","hits":511,"comments":7,"url":"http://bbs.ruliweb.com/community/board/300143/read/40460119?page=2","writeDt":1545807583000},{"order":108,"communityCode":"RULIWEB","bbsId":"300143","articleNo":40459834,"title":"세계 최초의 돌격소총 .jpg","writerType":"T","writer":"모에칸","hits":510,"comments":2,"url":"http://bbs.ruliweb.com/community/board/300143/read/40459834?page=1","writeDt":1545805835000},{"order":109,"communityCode":"RULIWEB","bbsId":"300143","articleNo":40460366,"title":"오네쇼타 대꼴 전개","writerType":"T","writer":"풀빵이","hits":509,"comments":3,"url":"http://bbs.ruliweb.com/community/board/300143/read/40460366?page=1","writeDt":1545808902000},{"order":110,"communityCode":"RULIWEB","bbsId":"300143","articleNo":40459475,"title":"수업시간에 옆자리 썸녀한테 쪽지보낸 남자","writerType":"T","writer":"진히로인 텐도아카네","hits":509,"comments":9,"url":"http://bbs.ruliweb.com/community/board/300143/read/40459475?page=3","writeDt":1545803875000},{"order":111,"communityCode":"RULIWEB","bbsId":"300143","articleNo":40457391,"title":"프로게이머들의 피지컬.JPG","writerType":"T","writer":"쿠르스와로","hits":508,"comments":9,"url":"http://bbs.ruliweb.com/community/board/300143/read/40457391?page=2","writeDt":1545791045000},{"order":112,"communityCode":"RULIWEB","bbsId":"300143","articleNo":40459215,"title":"베트남의 못 생기고 한복입은 20살 여대생","writerType":"T","writer":"루리웹-5457059761","hits":506,"comments":11,"url":"http://bbs.ruliweb.com/community/board/300143/read/40459215?page=1","writeDt":1545802303000},{"order":113,"communityCode":"RULIWEB","bbsId":"300143","articleNo":40460639,"title":"길 걸을때 남녀의 차이","writerType":"T","writer":"자레어","hits":505,"comments":16,"url":"http://bbs.ruliweb.com/community/board/300143/read/40460639?page=3","writeDt":1545810494000},{"order":114,"communityCode":"RULIWEB","bbsId":"300143","articleNo":40458973,"title":"극사실주의게임 철권.gif","writerType":"T","writer":"비스카르트","hits":505,"comments":3,"url":"http://bbs.ruliweb.com/community/board/300143/read/40458973?page=3","writeDt":1545800821000},{"order":115,"communityCode":"RULIWEB","bbsId":"300143","articleNo":40460454,"title":"일본 아침 출근길 지하철 광경","writerType":"T","writer":"오데뜨와 부뚜","hits":503,"comments":12,"url":"http://bbs.ruliweb.com/community/board/300143/read/40460454?page=2","writeDt":1545809433000},{"order":116,"communityCode":"RULIWEB","bbsId":"300143","articleNo":40458215,"title":"한국판 로컬라이징의 문제점","writerType":"T","writer":"Libértas:","hits":503,"comments":1,"url":"http://bbs.ruliweb.com/community/board/300143/read/40458215?page=2","writeDt":1545796322000},{"order":117,"communityCode":"RULIWEB","bbsId":"300143","articleNo":40459274,"title":"미국 근황","writerType":"T","writer":"AMONDAY","hits":502,"comments":2,"url":"http://bbs.ruliweb.com/community/board/300143/read/40459274?page=3","writeDt":1545802639000},{"order":118,"communityCode":"RULIWEB","bbsId":"300143","articleNo":40458867,"title":"역대급 뇌강.간.gif","writerType":"T","writer":"케이지","hits":502,"comments":4,"url":"http://bbs.ruliweb.com/community/board/300143/read/40458867?page=3","writeDt":1545800204000},{"order":119,"communityCode":"RULIWEB","bbsId":"300143","articleNo":40457651,"title":"저랑 검도 하지 않을래요?.jpg","writerType":"T","writer":"빌런냐옹","hits":502,"comments":3,"url":"http://bbs.ruliweb.com/community/board/300143/read/40457651?page=3","writeDt":1545792752000},{"order":120,"communityCode":"RULIWEB","bbsId":"300143","articleNo":40457942,"title":"특이점이 온 일식집.jpg","writerType":"T","writer":"O점","hits":500,"comments":6,"url":"http://bbs.ruliweb.com/community/board/300143/read/40457942?page=2","writeDt":1545794733000},{"order":121,"communityCode":"RULIWEB","bbsId":"300143","articleNo":40458918,"title":"요즘 고등학교 화장실.gif","writerType":"T","writer":"케이지","hits":499,"comments":7,"url":"http://bbs.ruliweb.com/community/board/300143/read/40458918?page=2","writeDt":1545800458000},{"order":122,"communityCode":"RULIWEB","bbsId":"300143","articleNo":40459161,"title":"공사판 양생 전문가 .gif","writerType":"T","writer":"메이거스의 검","hits":498,"comments":5,"url":"http://bbs.ruliweb.com/community/board/300143/read/40459161?page=3","writeDt":1545802018000},{"order":123,"communityCode":"RULIWEB","bbsId":"300143","articleNo":40458246,"title":"강등 호메떼","writerType":"T","writer":"옴닉사태","hits":497,"comments":7,"url":"http://bbs.ruliweb.com/community/board/300143/read/40458246?page=1","writeDt":1545796517000},{"order":124,"communityCode":"RULIWEB","bbsId":"300143","articleNo":40459726,"title":"동덕 여대 게시판 근황","writerType":"T","writer":"오데뜨와 부뚜","hits":497,"comments":9,"url":"http://bbs.ruliweb.com/community/board/300143/read/40459726?page=3","writeDt":1545805209000},{"order":125,"communityCode":"RULIWEB","bbsId":"300143","articleNo":40457822,"title":"(소전) 라플비 스킨 근황 (후방)","writerType":"T","writer":"초보유도가","hits":493,"comments":6,"url":"http://bbs.ruliweb.com/community/board/300143/read/40457822?page=2","writeDt":1545793986000},{"order":126,"communityCode":"RULIWEB","bbsId":"300143","articleNo":40460129,"title":"롤스로이스 후드 엠블럼 도난방지","writerType":"T","writer":"키넛","hits":493,"comments":11,"url":"http://bbs.ruliweb.com/community/board/300143/read/40460129?page=2","writeDt":1545807634000},{"order":127,"communityCode":"RULIWEB","bbsId":"300143","articleNo":40458211,"title":"생존형 광고 원탑.GIF","writerType":"T","writer":"심슨o","hits":493,"comments":2,"url":"http://bbs.ruliweb.com/community/board/300143/read/40458211?page=2","writeDt":1545796305000},{"order":128,"communityCode":"RULIWEB","bbsId":"300143","articleNo":40459159,"title":"거유 여고생과 빈유 여고생 백합 만화.manga","writerType":"T","writer":"식봉식봉이","hits":492,"comments":0,"url":"http://bbs.ruliweb.com/community/board/300143/read/40459159?page=3","writeDt":1545801991000},{"order":129,"communityCode":"RULIWEB","bbsId":"300143","articleNo":40457584,"title":"대학교 인싸카톡 근황","writerType":"T","writer":"부들부들™","hits":491,"comments":7,"url":"http://bbs.ruliweb.com/community/board/300143/read/40457584?page=2","writeDt":1545792317000},{"order":130,"communityCode":"RULIWEB","bbsId":"300143","articleNo":40458182,"title":"돌도 섻스를 합니다","writerType":"T","writer":"서비스가보답","hits":491,"comments":1,"url":"http://bbs.ruliweb.com/community/board/300143/read/40458182?page=3","writeDt":1545796141000},{"order":131,"communityCode":"RULIWEB","bbsId":"300143","articleNo":40457482,"title":"이렇게 예뻤나?","writerType":"T","writer":"가슴매니아","hits":490,"comments":12,"url":"http://bbs.ruliweb.com/community/board/300143/read/40457482?page=2","writeDt":1545791660000},{"order":132,"communityCode":"RULIWEB","bbsId":"300143","articleNo":40457570,"title":"강아지를 밟으면 19조원을 줍니다!","writerType":"T","writer":"슬라네쉬숭배자","hits":489,"comments":10,"url":"http://bbs.ruliweb.com/community/board/300143/read/40457570?page=3","writeDt":1545792212000},{"order":133,"communityCode":"RULIWEB","bbsId":"300143","articleNo":40459097,"title":"드래곤볼 미화 캐릭터","writerType":"T","writer":"ㅎㄴㅋㅌ23","hits":487,"comments":5,"url":"http://bbs.ruliweb.com/community/board/300143/read/40459097?page=2","writeDt":1545801583000},{"order":134,"communityCode":"RULIWEB","bbsId":"300143","articleNo":40460009,"title":"오빠 나 젖어떠","writerType":"T","writer":"쯔위입니다","hits":487,"comments":4,"url":"http://bbs.ruliweb.com/community/board/300143/read/40460009?page=2","writeDt":1545806969000},{"order":135,"communityCode":"RULIWEB","bbsId":"300143","articleNo":40457718,"title":"운전자를 유혹하는..gif","writerType":"T","writer":"Red Velvet","hits":487,"comments":4,"url":"http://bbs.ruliweb.com/community/board/300143/read/40457718?page=3","writeDt":1545793180000},{"order":136,"communityCode":"RULIWEB","bbsId":"300143","articleNo":40460220,"title":"요스가노소라 현실 반영","writerType":"T","writer":"스타라이트","hits":486,"comments":5,"url":"http://bbs.ruliweb.com/community/board/300143/read/40460220?page=3","writeDt":1545808144000},{"order":137,"communityCode":"RULIWEB","bbsId":"300143","articleNo":40457678,"title":"논란이 되지않는 근친상간물","writerType":"T","writer":"長門有希","hits":485,"comments":7,"url":"http://bbs.ruliweb.com/community/board/300143/read/40457678?page=2","writeDt":1545792957000},{"order":138,"communityCode":"RULIWEB","bbsId":"300143","articleNo":40458878,"title":"생활의 달인 레전드 등장씬.gif","writerType":"T","writer":"ventriloquism","hits":484,"comments":3,"url":"http://bbs.ruliweb.com/community/board/300143/read/40458878?page=3","writeDt":1545800252000},{"order":139,"communityCode":"RULIWEB","bbsId":"300143","articleNo":40458518,"title":"화이트메인 : 심판을 시작한다!","writerType":"T","writer":"오르피아 똥꼬냄새","hits":483,"comments":14,"url":"http://bbs.ruliweb.com/community/board/300143/read/40458518?page=2","writeDt":1545798164000},{"order":140,"communityCode":"RULIWEB","bbsId":"300143","articleNo":40460651,"title":"디즈니 스파게티 씬 재현.GIF","writerType":"T","writer":"키넛","hits":483,"comments":3,"url":"http://bbs.ruliweb.com/community/board/300143/read/40460651?page=3","writeDt":1545810565000},{"order":141,"communityCode":"RULIWEB","bbsId":"300143","articleNo":40459803,"title":"더파이팅 근황.jpg","writerType":"T","writer":"타마고로","hits":482,"comments":10,"url":"http://bbs.ruliweb.com/community/board/300143/read/40459803?page=2","writeDt":1545805653000},{"order":142,"communityCode":"RULIWEB","bbsId":"300143","articleNo":40460662,"title":"중국으로 여행가자","writerType":"T","writer":"유우키 아오이","hits":482,"comments":7,"url":"http://bbs.ruliweb.com/community/board/300143/read/40460662?page=2","writeDt":1545810603000},{"order":143,"communityCode":"RULIWEB","bbsId":"300143","articleNo":40458651,"title":"역대급 제목학원 .jpg","writerType":"T","writer":"하루 에스티아","hits":482,"comments":6,"url":"http://bbs.ruliweb.com/community/board/300143/read/40458651?page=3","writeDt":1545798925000},{"order":144,"communityCode":"RULIWEB","bbsId":"300143","articleNo":40458984,"title":"오또케 축구짤","writerType":"T","writer":"쩌곰","hits":482,"comments":3,"url":"http://bbs.ruliweb.com/community/board/300143/read/40458984?page=2","writeDt":1545800862000},{"order":145,"communityCode":"RULIWEB","bbsId":"300143","articleNo":40459386,"title":"혜리 스타일리스트 실력","writerType":"T","writer":"쯔위입니다","hits":480,"comments":4,"url":"http://bbs.ruliweb.com/community/board/300143/read/40459386?page=2","writeDt":1545803302000},{"order":146,"communityCode":"RULIWEB","bbsId":"300143","articleNo":40459909,"title":"돌싱 단톡방 침투.jpg","writerType":"T","writer":"부들부들™","hits":479,"comments":9,"url":"http://bbs.ruliweb.com/community/board/300143/read/40459909?page=2","writeDt":1545806406000},{"order":147,"communityCode":"RULIWEB","bbsId":"300143","articleNo":40458213,"title":"유희왕 최고의 병맛 카드.jpg","writerType":"T","writer":"죄수번호-00000000","hits":478,"comments":4,"url":"http://bbs.ruliweb.com/community/board/300143/read/40458213?page=2","writeDt":1545796312000},{"order":148,"communityCode":"RULIWEB","bbsId":"300143","articleNo":40457453,"title":"화난 서양여자","writerType":"T","writer":"하즈키료2","hits":476,"comments":2,"url":"http://bbs.ruliweb.com/community/board/300143/read/40457453?page=3","writeDt":1545791479000},{"order":149,"communityCode":"RULIWEB","bbsId":"300143","articleNo":40458712,"title":"공포의 일본도","writerType":"T","writer":"놀러갈께","hits":474,"comments":5,"url":"http://bbs.ruliweb.com/community/board/300143/read/40458712?page=1","writeDt":1545799238000},{"order":150,"communityCode":"RULIWEB","bbsId":"300143","articleNo":40458536,"title":"흔치않은 PC방 컴터 사양","writerType":"T","writer":"340456694","hits":472,"comments":19,"url":"http://bbs.ruliweb.com/community/board/300143/read/40458536?page=1","writeDt":1545798280000},{"order":151,"communityCode":"RULIWEB","bbsId":"300143","articleNo":40458696,"title":"일주일 뒤면 개봉한지 18년 되는 영화 .jpg","writerType":"T","writer":"하루 에스티아","hits":472,"comments":12,"url":"http://bbs.ruliweb.com/community/board/300143/read/40458696?page=2","writeDt":1545799132000},{"order":152,"communityCode":"RULIWEB","bbsId":"300143","articleNo":40459754,"title":"음주운전 처벌이 강화된 한국 근황","writerType":"T","writer":"리링냥","hits":472,"comments":7,"url":"http://bbs.ruliweb.com/community/board/300143/read/40459754?page=2","writeDt":1545805389000},{"order":153,"communityCode":"RULIWEB","bbsId":"300143","articleNo":40457225,"title":"웃대의 미 친 드립ㅋㅋㅋㅋㅋㅋㅋㅋㅋㅋㅋㅋㅋㅋㅋ","writerType":"T","writer":"진히로인 텐도아카네","hits":471,"comments":5,"url":"http://bbs.ruliweb.com/community/board/300143/read/40457225?page=2","writeDt":1545789955000},{"order":154,"communityCode":"RULIWEB","bbsId":"300143","articleNo":40459082,"title":"히치하이크 하는 manhwa","writerType":"T","writer":"풀빵이","hits":471,"comments":8,"url":"http://bbs.ruliweb.com/community/board/300143/read/40459082?page=2","writeDt":1545801506000},{"order":155,"communityCode":"RULIWEB","bbsId":"300143","articleNo":40457804,"title":"안경, 주근깨, 모에속성.","writerType":"T","writer":"부르마핥짝","hits":469,"comments":5,"url":"http://bbs.ruliweb.com/community/board/300143/read/40457804?page=3","writeDt":1545793856000},{"order":156,"communityCode":"RULIWEB","bbsId":"300143","articleNo":40459155,"title":"여자 연예인 본 김희철 표정","writerType":"T","writer":"쯔위입니다","hits":469,"comments":3,"url":"http://bbs.ruliweb.com/community/board/300143/read/40459155?page=3","writeDt":1545801979000},{"order":157,"communityCode":"RULIWEB","bbsId":"300143","articleNo":40457626,"title":"(히로아카)라면집에 처음 와 본 반반무마니.manga","writerType":"T","writer":"식봉식봉이","hits":469,"comments":7,"url":"http://bbs.ruliweb.com/community/board/300143/read/40457626?page=1","writeDt":1545792552000},{"order":158,"communityCode":"RULIWEB","bbsId":"300143","articleNo":40457426,"title":"한국 수준 미개 그 자체네ㅋㅋㅋㅋ","writerType":"T","writer":"지그지그지그","hits":469,"comments":6,"url":"http://bbs.ruliweb.com/community/board/300143/read/40457426?page=1","writeDt":1545791251000},{"order":159,"communityCode":"RULIWEB","bbsId":"300143","articleNo":40459751,"title":"사람들은 잘 모르는 미식축구 필승법.gif","writerType":"T","writer":"하은선혜","hits":468,"comments":9,"url":"http://bbs.ruliweb.com/community/board/300143/read/40459751?page=2","writeDt":1545805335000},{"order":160,"communityCode":"RULIWEB","bbsId":"300143","articleNo":40459270,"title":"다키스트 던전은 이런 게임입니다.","writerType":"T","writer":"몬스터에너지","hits":467,"comments":7,"url":"http://bbs.ruliweb.com/community/board/300143/read/40459270?page=3","writeDt":1545802617000},{"order":161,"communityCode":"RULIWEB","bbsId":"300143","articleNo":40458815,"title":"어휴 고인물들 진흙바닥 싸움 수준.gif","writerType":"T","writer":"人生無想","hits":467,"comments":5,"url":"http://bbs.ruliweb.com/community/board/300143/read/40458815?page=2","writeDt":1545799836000},{"order":162,"communityCode":"RULIWEB","bbsId":"300143","articleNo":40459812,"title":"픽사 무비 코코를 보는 관객들 심정","writerType":"T","writer":"error37","hits":465,"comments":13,"url":"http://bbs.ruliweb.com/community/board/300143/read/40459812?page=2","writeDt":1545805699000},{"order":163,"communityCode":"RULIWEB","bbsId":"300143","articleNo":40459010,"title":"강호동 상의 탈의 반응","writerType":"T","writer":"쯔위입니다","hits":464,"comments":11,"url":"http://bbs.ruliweb.com/community/board/300143/read/40459010?page=1","writeDt":1545801051000},{"order":164,"communityCode":"RULIWEB","bbsId":"300143","articleNo":40458779,"title":"리액션 혜자","writerType":"T","writer":"루리웹-6180343270","hits":464,"comments":3,"url":"http://bbs.ruliweb.com/community/board/300143/read/40458779?page=3","writeDt":1545799621000},{"order":165,"communityCode":"RULIWEB","bbsId":"300143","articleNo":40459059,"title":"시구하러 온 골드문 회장님.gif","writerType":"T","writer":"ventriloquism","hits":464,"comments":4,"url":"http://bbs.ruliweb.com/community/board/300143/read/40459059?page=3","writeDt":1545801367000},{"order":166,"communityCode":"RULIWEB","bbsId":"300143","articleNo":40459080,"title":"개존맛인데도 이상할 정도로 일본 매체에서는 찬밥인 과자.jpg","writerType":"T","writer":"밤과낮 그사이로","hits":464,"comments":13,"url":"http://bbs.ruliweb.com/community/board/300143/read/40459080?page=3","writeDt":1545801485000},{"order":167,"communityCode":"RULIWEB","bbsId":"300143","articleNo":40459783,"title":"동물원 놀러 갔다가 죽을뻔한 타이슨 .jpg","writerType":"T","writer":"모에칸","hits":462,"comments":4,"url":"http://bbs.ruliweb.com/community/board/300143/read/40459783?page=1","writeDt":1545805558000},{"order":168,"communityCode":"RULIWEB","bbsId":"300143","articleNo":40459078,"title":"지방사람은 이해 못하는것 .jpg","writerType":"T","writer":"메이거스의 검","hits":461,"comments":8,"url":"http://bbs.ruliweb.com/community/board/300143/read/40459078?page=3","writeDt":1545801479000},{"order":169,"communityCode":"RULIWEB","bbsId":"300143","articleNo":40459739,"title":"성능 쩌는 카메라.","writerType":"T","writer":"사이가도(彩画堂)","hits":461,"comments":4,"url":"http://bbs.ruliweb.com/community/board/300143/read/40459739?page=2","writeDt":1545805278000},{"order":170,"communityCode":"RULIWEB","bbsId":"300143","articleNo":40457936,"title":"현재 검열당한 벽람 신년 스킨","writerType":"T","writer":"메이즈 폭렬시공","hits":460,"comments":4,"url":"http://bbs.ruliweb.com/community/board/300143/read/40457936?page=2","writeDt":1545794713000},{"order":171,"communityCode":"RULIWEB","bbsId":"300143","articleNo":40457247,"title":"역시 피자는.jpg","writerType":"T","writer":"부들부들™","hits":459,"comments":5,"url":"http://bbs.ruliweb.com/community/board/300143/read/40457247?page=1","writeDt":1545790124000},{"order":172,"communityCode":"RULIWEB","bbsId":"300143","articleNo":40458804,"title":"쿄애니 사상 역대급으로 관심이 적은애니..","writerType":"T","writer":"ang경사나이","hits":459,"comments":9,"url":"http://bbs.ruliweb.com/community/board/300143/read/40458804?page=2","writeDt":1545799781000},{"order":173,"communityCode":"RULIWEB","bbsId":"300143","articleNo":40459363,"title":"쿠노이치의 암살.HugeTits","writerType":"T","writer":"오르피아 똥꼬냄새","hits":459,"comments":7,"url":"http://bbs.ruliweb.com/community/board/300143/read/40459363?page=3","writeDt":1545803202000},{"order":174,"communityCode":"RULIWEB","bbsId":"300143","articleNo":40457386,"title":"방송 사고 날뻔한 조보아","writerType":"T","writer":"silver line","hits":458,"comments":6,"url":"http://bbs.ruliweb.com/community/board/300143/read/40457386?page=2","writeDt":1545791017000},{"order":175,"communityCode":"RULIWEB","bbsId":"300143","articleNo":40458987,"title":"사스케의 또하나의 이불킥 사건","writerType":"T","writer":"RubyEyed","hits":458,"comments":4,"url":"http://bbs.ruliweb.com/community/board/300143/read/40458987?page=2","writeDt":1545800888000},{"order":176,"communityCode":"RULIWEB","bbsId":"300143","articleNo":40457454,"title":"슈퍼맨 파워 연출 레전드","writerType":"T","writer":"블랙스마일","hits":458,"comments":4,"url":"http://bbs.ruliweb.com/community/board/300143/read/40457454?page=3","writeDt":1545791481000},{"order":177,"communityCode":"RULIWEB","bbsId":"300143","articleNo":40457388,"title":"만난지 1분만에 고백하는 오타쿠.jpg","writerType":"T","writer":"부들부들™","hits":457,"comments":8,"url":"http://bbs.ruliweb.com/community/board/300143/read/40457388?page=2","writeDt":1545791032000},{"order":178,"communityCode":"RULIWEB","bbsId":"300143","articleNo":40458193,"title":"많은 사람들의 죽음을 목격하고 무언가를 결심한 빌런","writerType":"T","writer":"에버샤이닝","hits":457,"comments":3,"url":"http://bbs.ruliweb.com/community/board/300143/read/40458193?page=3","writeDt":1545796181000},{"order":179,"communityCode":"RULIWEB","bbsId":"300143","articleNo":40460558,"title":"양아치들이 수학을 공부한 이유.jpg(下편)","writerType":"T","writer":"부들부들™","hits":455,"comments":3,"url":"http://bbs.ruliweb.com/community/board/300143/read/40460558?page=2","writeDt":1545810038000},{"order":180,"communityCode":"RULIWEB","bbsId":"300143","articleNo":40459911,"title":"몇세기 동안 바보짓을 해온 암살 단체","writerType":"T","writer":"Myoong","hits":455,"comments":17,"url":"http://bbs.ruliweb.com/community/board/300143/read/40459911?page=2","writeDt":1545806408000},{"order":181,"communityCode":"RULIWEB","bbsId":"300143","articleNo":40458913,"title":"나이 먹고 보니 애국자 ..jpg","writerType":"T","writer":"메이거스의 검","hits":455,"comments":6,"url":"http://bbs.ruliweb.com/community/board/300143/read/40458913?page=2","writeDt":1545800441000},{"order":182,"communityCode":"RULIWEB","bbsId":"300143","articleNo":40457723,"title":"편의점 알바생이 역대급으로 이쁜경우 편의점 사장님반응","writerType":"T","writer":"error37","hits":455,"comments":7,"url":"http://bbs.ruliweb.com/community/board/300143/read/40457723?page=3","writeDt":1545793238000},{"order":183,"communityCode":"RULIWEB","bbsId":"300143","articleNo":40460360,"title":"상성이 도무지 이해 안되는 포켓몬.JPG","writerType":"T","writer":"네모 건달","hits":454,"comments":2,"url":"http://bbs.ruliweb.com/community/board/300143/read/40460360?page=1","writeDt":1545808858000},{"order":184,"communityCode":"RULIWEB","bbsId":"300143","articleNo":40458805,"title":"아무도 도와주지 못했다는 전설의 그사건..","writerType":"T","writer":"놀러갈께","hits":452,"comments":13,"url":"http://bbs.ruliweb.com/community/board/300143/read/40458805?page=2","writeDt":1545799788000},{"order":185,"communityCode":"RULIWEB","bbsId":"300143","articleNo":40459174,"title":"???: 가난한 새퀴가 돈가스를 먹어?! jpg","writerType":"T","writer":"전↗ 복↘","hits":452,"comments":9,"url":"http://bbs.ruliweb.com/community/board/300143/read/40459174?page=3","writeDt":1545802115000},{"order":186,"communityCode":"RULIWEB","bbsId":"300143","articleNo":40459278,"title":"알기 쉬운 카페메뉴","writerType":"T","writer":"쯔위입니다","hits":450,"comments":8,"url":"http://bbs.ruliweb.com/community/board/300143/read/40459278?page=2","writeDt":1545802654000},{"order":187,"communityCode":"RULIWEB","bbsId":"300143","articleNo":40460356,"title":"???:사유재산 인정해라 빼액!","writerType":"T","writer":"좌절중orz","hits":450,"comments":5,"url":"http://bbs.ruliweb.com/community/board/300143/read/40460356?page=2","writeDt":1545808838000},{"order":188,"communityCode":"RULIWEB","bbsId":"300143","articleNo":40458955,"title":"국적불명의 음식점 .jpg","writerType":"T","writer":"메이거스의 검","hits":449,"comments":7,"url":"http://bbs.ruliweb.com/community/board/300143/read/40458955?page=3","writeDt":1545800725000},{"order":189,"communityCode":"RULIWEB","bbsId":"300143","articleNo":40459877,"title":"2018년 상반기 한국 콘텐츠산업 수출량","writerType":"T","writer":"테레사 아포칼립스","hits":448,"comments":5,"url":"http://bbs.ruliweb.com/community/board/300143/read/40459877?page=3","writeDt":1545806122000},{"order":190,"communityCode":"RULIWEB","bbsId":"300143","articleNo":40459516,"title":"군대 다녀온 남자들 단체로 발작 일으키게 만드는 사진들 .jpg","writerType":"T","writer":"하루 에스티아","hits":448,"comments":13,"url":"http://bbs.ruliweb.com/community/board/300143/read/40459516?page=2","writeDt":1545804110000},{"order":191,"communityCode":"RULIWEB","bbsId":"300143","articleNo":40459124,"title":"2400년전 인공호흡법.jpg","writerType":"T","writer":"포근한요리사","hits":447,"comments":6,"url":"http://bbs.ruliweb.com/community/board/300143/read/40459124?page=1","writeDt":1545801775000},{"order":192,"communityCode":"RULIWEB","bbsId":"300143","articleNo":40457932,"title":"아무리 봐도 치녀복장인데 안야함","writerType":"T","writer":"간다무간다무","hits":447,"comments":4,"url":"http://bbs.ruliweb.com/community/board/300143/read/40457932?page=2","writeDt":1545794708000},{"order":193,"communityCode":"RULIWEB","bbsId":"300143","articleNo":40457213,"title":"헬스장의 악마.gif","writerType":"T","writer":"아론다이트","hits":447,"comments":2,"url":"http://bbs.ruliweb.com/community/board/300143/read/40457213?page=2","writeDt":1545789887000},{"order":194,"communityCode":"RULIWEB","bbsId":"300143","articleNo":40458483,"title":"공포의 최애캐 생일광고.jpg","writerType":"T","writer":"로제마인™","hits":446,"comments":7,"url":"http://bbs.ruliweb.com/community/board/300143/read/40458483?page=3","writeDt":1545797967000},{"order":195,"communityCode":"RULIWEB","bbsId":"300143","articleNo":40457744,"title":"'여친 몰카 인증' 일베 무더기 검거..\"관심 받고 싶어서\"","writerType":"T","writer":"부르마핥짝","hits":445,"comments":3,"url":"http://bbs.ruliweb.com/community/board/300143/read/40457744?page=2","writeDt":1545793387000},{"order":196,"communityCode":"RULIWEB","bbsId":"300143","articleNo":40459804,"title":"로리콘의 천국 ^,^","writerType":"T","writer":"샤스르리에어","hits":445,"comments":13,"url":"http://bbs.ruliweb.com/community/board/300143/read/40459804?page=2","writeDt":1545805660000},{"order":197,"communityCode":"RULIWEB","bbsId":"300143","articleNo":40458992,"title":"둘중에 한명과 술을 마셔야만 한다면","writerType":"T","writer":"오르피아 똥꼬냄새","hits":445,"comments":13,"url":"http://bbs.ruliweb.com/community/board/300143/read/40458992?page=2","writeDt":1545800944000},{"order":198,"communityCode":"RULIWEB","bbsId":"300143","articleNo":40457286,"title":"학원도시의 위대함을 알 수 있는 짤.jpg","writerType":"T","writer":"식봉식봉이","hits":443,"comments":2,"url":"http://bbs.ruliweb.com/community/board/300143/read/40457286?page=3","writeDt":1545790454000},{"order":199,"communityCode":"RULIWEB","bbsId":"300143","articleNo":40457851,"title":"컴퓨터 유냉식 쿨러.gif","writerType":"T","writer":"Red Velvet","hits":440,"comments":6,"url":"http://bbs.ruliweb.com/community/board/300143/read/40457851?page=1","writeDt":1545794184000},{"order":200,"communityCode":"RULIWEB","bbsId":"300143","articleNo":40457476,"title":"와이프한테 욕할 절호의 찬스","writerType":"T","writer":"코토하P","hits":439,"comments":3,"url":"http://bbs.ruliweb.com/community/board/300143/read/40457476?page=2","writeDt":1545791629000},{"order":201,"communityCode":"RULIWEB","bbsId":"300143","articleNo":40458812,"title":"페도 사냥꾼 애니","writerType":"T","writer":"오르피아 똥꼬냄새","hits":439,"comments":5,"url":"http://bbs.ruliweb.com/community/board/300143/read/40458812?page=2","writeDt":1545799820000},{"order":202,"communityCode":"RULIWEB","bbsId":"300143","articleNo":40457580,"title":"바쿠레기 핵폐기물 만드는 만화.manga","writerType":"T","writer":"식봉식봉이","hits":439,"comments":5,"url":"http://bbs.ruliweb.com/community/board/300143/read/40457580?page=2","writeDt":1545792255000},{"order":203,"communityCode":"RULIWEB","bbsId":"300143","articleNo":40460090,"title":"어벤져스 승리 공식","writerType":"T","writer":"에티리얼","hits":438,"comments":7,"url":"http://bbs.ruliweb.com/community/board/300143/read/40460090?page=3","writeDt":1545807434000},{"order":204,"communityCode":"RULIWEB","bbsId":"300143","articleNo":40457401,"title":"세븐나이츠 어뷰징사건.jpg","writerType":"T","writer":"빅짤방맨","hits":438,"comments":4,"url":"http://bbs.ruliweb.com/community/board/300143/read/40457401?page=2","writeDt":1545791111000},{"order":205,"communityCode":"RULIWEB","bbsId":"300143","articleNo":40457661,"title":"애니프사 카카오톡 모음","writerType":"T","writer":"Hearts_of_Iron","hits":438,"comments":9,"url":"http://bbs.ruliweb.com/community/board/300143/read/40457661?page=2","writeDt":1545792826000},{"order":206,"communityCode":"RULIWEB","bbsId":"300143","articleNo":40457679,"title":"대륙의 가상화폐 jpg","writerType":"T","writer":"거칠마루잉","hits":438,"comments":8,"url":"http://bbs.ruliweb.com/community/board/300143/read/40457679?page=2","writeDt":1545792968000},{"order":207,"communityCode":"RULIWEB","bbsId":"300143","articleNo":40458962,"title":"한국 생활에 찌든 외국인이 귀국했을 때 모습.jpg","writerType":"T","writer":"ventriloquism","hits":438,"comments":2,"url":"http://bbs.ruliweb.com/community/board/300143/read/40458962?page=3","writeDt":1545800756000},{"order":208,"communityCode":"RULIWEB","bbsId":"300143","articleNo":40460327,"title":"트랜스포머 피규어 저작권 근황 .jpg","writerType":"T","writer":"메이거스의 검","hits":437,"comments":4,"url":"http://bbs.ruliweb.com/community/board/300143/read/40460327?page=3","writeDt":1545808686000},{"order":209,"communityCode":"RULIWEB","bbsId":"300143","articleNo":40460451,"title":"벌받은 부먹파","writerType":"T","writer":"레드쥬스","hits":437,"comments":7,"url":"http://bbs.ruliweb.com/community/board/300143/read/40460451?page=2","writeDt":1545809410000},{"order":210,"communityCode":"RULIWEB","bbsId":"300143","articleNo":40457379,"title":"분수싸는 하늘보리녀 .AVI","writerType":"T","writer":"가란 크로","hits":436,"comments":8,"url":"http://bbs.ruliweb.com/community/board/300143/read/40457379?page=3","writeDt":1545790991000},{"order":211,"communityCode":"RULIWEB","bbsId":"300143","articleNo":40457387,"title":"흔한 컴퓨터 열 식히는 방법","writerType":"T","writer":"루리웹-0184090821","hits":436,"comments":17,"url":"http://bbs.ruliweb.com/community/board/300143/read/40457387?page=2","writeDt":1545791020000},{"order":212,"communityCode":"RULIWEB","bbsId":"300143","articleNo":40458993,"title":"백종원의 시간은 거꾸로 간다.jpg","writerType":"T","writer":"ventriloquism","hits":435,"comments":2,"url":"http://bbs.ruliweb.com/community/board/300143/read/40458993?page=2","writeDt":1545800944000},{"order":213,"communityCode":"RULIWEB","bbsId":"300143","articleNo":40457645,"title":"??? : 이영표 이 자식...","writerType":"T","writer":"유우키 아오이","hits":434,"comments":8,"url":"http://bbs.ruliweb.com/community/board/300143/read/40457645?page=3","writeDt":1545792687000},{"order":214,"communityCode":"RULIWEB","bbsId":"300143","articleNo":40459005,"title":"반박불가 1~4화까진 쩔었던 애니 .gif","writerType":"T","writer":"하루 에스티아","hits":434,"comments":4,"url":"http://bbs.ruliweb.com/community/board/300143/read/40459005?page=2","writeDt":1545801018000},{"order":215,"communityCode":"RULIWEB","bbsId":"300143","articleNo":40459258,"title":"소울워커에서 이상하게 저평가 받는 지역 스토리 .jpg","writerType":"T","writer":"하루 에스티아","hits":433,"comments":10,"url":"http://bbs.ruliweb.com/community/board/300143/read/40459258?page=3","writeDt":1545802544000},{"order":216,"communityCode":"RULIWEB","bbsId":"300143","articleNo":40457227,"title":"탕수육이란 값싼 고기를 그럴듯하게 팔려고 만든 음식이에요","writerType":"T","writer":"메가보만다","hits":432,"comments":15,"url":"http://bbs.ruliweb.com/community/board/300143/read/40457227?page=2","writeDt":1545789982000},{"order":217,"communityCode":"RULIWEB","bbsId":"300143","articleNo":40457241,"title":"충격적인 악당의 복지.jpg","writerType":"T","writer":"쿠르스와로","hits":432,"comments":3,"url":"http://bbs.ruliweb.com/community/board/300143/read/40457241?page=1","writeDt":1545790079000},{"order":218,"communityCode":"RULIWEB","bbsId":"300143","articleNo":40457272,"title":"포탈에서 모두가 해보는 일.gif","writerType":"T","writer":"식봉식봉이","hits":432,"comments":6,"url":"http://bbs.ruliweb.com/community/board/300143/read/40457272?page=3","writeDt":1545790331000},{"order":219,"communityCode":"RULIWEB","bbsId":"300143","articleNo":40460677,"title":"특전사의 위엄","writerType":"T","writer":"어죽어죽","hits":432,"comments":13,"url":"http://bbs.ruliweb.com/community/board/300143/read/40460677?page=2","writeDt":1545810705000},{"order":220,"communityCode":"RULIWEB","bbsId":"300143","articleNo":40458983,"title":"러시아식 인질 구출","writerType":"T","writer":"루리웹-6180343270","hits":432,"comments":2,"url":"http://bbs.ruliweb.com/community/board/300143/read/40458983?page=2","writeDt":1545800857000},{"order":221,"communityCode":"RULIWEB","bbsId":"300143","articleNo":40460680,"title":"굳이 만들 필요 없었던 신형기","writerType":"T","writer":"치르47","hits":431,"comments":3,"url":"http://bbs.ruliweb.com/community/board/300143/read/40460680?page=2","writeDt":1545810748000},{"order":222,"communityCode":"RULIWEB","bbsId":"300143","articleNo":40458652,"title":"모에테키타 근황.jpg","writerType":"T","writer":"ㅎㄴㅋㅌ23","hits":431,"comments":0,"url":"http://bbs.ruliweb.com/community/board/300143/read/40458652?page=3","writeDt":1545798933000},{"order":223,"communityCode":"RULIWEB","bbsId":"300143","articleNo":40458792,"title":"2019 기대 신작 게임","writerType":"T","writer":"정력왕조루내시","hits":430,"comments":4,"url":"http://bbs.ruliweb.com/community/board/300143/read/40458792?page=3","writeDt":1545799710000},{"order":224,"communityCode":"RULIWEB","bbsId":"300143","articleNo":40457301,"title":"[약후] 팬티의 종류","writerType":"T","writer":"케이지","hits":430,"comments":2,"url":"http://bbs.ruliweb.com/community/board/300143/read/40457301?page=2","writeDt":1545790560000},{"order":225,"communityCode":"RULIWEB","bbsId":"300143","articleNo":40457659,"title":"(히로아카)거짓말하는 야오모몽 만화.manga","writerType":"T","writer":"식봉식봉이","hits":430,"comments":2,"url":"http://bbs.ruliweb.com/community/board/300143/read/40457659?page=2","writeDt":1545792807000},{"order":226,"communityCode":"RULIWEB","bbsId":"300143","articleNo":40457736,"title":"현실적인 여전사가 등장하는 게임","writerType":"T","writer":"로보보","hits":429,"comments":2,"url":"http://bbs.ruliweb.com/community/board/300143/read/40457736?page=2","writeDt":1545793312000},{"order":227,"communityCode":"RULIWEB","bbsId":"300143","articleNo":40457230,"title":"호불호 갈리는 꼬치.jpg","writerType":"T","writer":"쿠르스와로","hits":429,"comments":7,"url":"http://bbs.ruliweb.com/community/board/300143/read/40457230?page=2","writeDt":1545789998000},{"order":228,"communityCode":"RULIWEB","bbsId":"300143","articleNo":40459595,"title":"여자들도 몸매좋은 여자 좋아하더라","writerType":"T","writer":"부르마핥짝","hits":429,"comments":9,"url":"http://bbs.ruliweb.com/community/board/300143/read/40459595?page=3","writeDt":1545804553000},{"order":229,"communityCode":"RULIWEB","bbsId":"300143","articleNo":40459704,"title":"페이트 아쳐 스테이터스 1위","writerType":"T","writer":"주님","hits":429,"comments":14,"url":"http://bbs.ruliweb.com/community/board/300143/read/40459704?page=3","writeDt":1545805081000},{"order":230,"communityCode":"RULIWEB","bbsId":"300143","articleNo":40459775,"title":"여자친구 오빠가 파이터.jpg","writerType":"T","writer":"부들부들™","hits":429,"comments":0,"url":"http://bbs.ruliweb.com/community/board/300143/read/40459775?page=1","writeDt":1545805514000},{"order":231,"communityCode":"RULIWEB","bbsId":"300143","articleNo":40457370,"title":"꼬리가 너무 작아서 부끄러워요.jpg","writerType":"T","writer":"빌런냐옹","hits":428,"comments":2,"url":"http://bbs.ruliweb.com/community/board/300143/read/40457370?page=3","writeDt":1545790939000},{"order":232,"communityCode":"RULIWEB","bbsId":"300143","articleNo":40457450,"title":"분자 구조 쉽게 외우는 방법.jpg","writerType":"T","writer":"쿠르스와로","hits":428,"comments":2,"url":"http://bbs.ruliweb.com/community/board/300143/read/40457450?page=3","writeDt":1545791452000},{"order":233,"communityCode":"RULIWEB","bbsId":"300143","articleNo":40460529,"title":"남자의 로망과도 같은 무기들","writerType":"T","writer":"루리웹-6180343270","hits":427,"comments":2,"url":"http://bbs.ruliweb.com/community/board/300143/read/40460529?page=3","writeDt":1545809881000},{"order":234,"communityCode":"RULIWEB","bbsId":"300143","articleNo":40459801,"title":"(스포) 알고보니 자기 자신을 최애캐로 빨아던 캐릭터","writerType":"T","writer":"Myoong","hits":426,"comments":3,"url":"http://bbs.ruliweb.com/community/board/300143/read/40459801?page=2","writeDt":1545805633000},{"order":235,"communityCode":"RULIWEB","bbsId":"300143","articleNo":40459296,"title":"공연 도중 쓰나미…","writerType":"T","writer":"쯔위입니다","hits":426,"comments":3,"url":"http://bbs.ruliweb.com/community/board/300143/read/40459296?page=2","writeDt":1545802787000},{"order":236,"communityCode":"RULIWEB","bbsId":"300143","articleNo":40459596,"title":"바위마을을 지도에서 없애 버릴려는 시카마루.jpg","writerType":"T","writer":"블러드 스타크","hits":426,"comments":6,"url":"http://bbs.ruliweb.com/community/board/300143/read/40459596?page=3","writeDt":1545804556000},{"order":237,"communityCode":"RULIWEB","bbsId":"300143","articleNo":40460630,"title":"좀비랜드사가 12화 일본 반응.nicodon","writerType":"T","writer":"초보유도가","hits":426,"comments":8,"url":"http://bbs.ruliweb.com/community/board/300143/read/40460630?page=3","writeDt":1545810439000},{"order":238,"communityCode":"RULIWEB","bbsId":"300143","articleNo":40458687,"title":"엄마가 싸준 음식 개 주는 와이프","writerType":"T","writer":"아사히 슈퍼드라이","hits":426,"comments":6,"url":"http://bbs.ruliweb.com/community/board/300143/read/40458687?page=2","writeDt":1545799086000},{"order":239,"communityCode":"RULIWEB","bbsId":"300143","articleNo":40458718,"title":"외국인의 LG리뷰.jpg","writerType":"T","writer":"앸시스","hits":426,"comments":2,"url":"http://bbs.ruliweb.com/community/board/300143/read/40458718?page=1","writeDt":1545799279000},{"order":240,"communityCode":"RULIWEB","bbsId":"300143","articleNo":40460018,"title":"여유로운 유영","writerType":"T","writer":"오데뜨와 부뚜","hits":425,"comments":4,"url":"http://bbs.ruliweb.com/community/board/300143/read/40460018?page=2","writeDt":1545807003000},{"order":241,"communityCode":"RULIWEB","bbsId":"300143","articleNo":40457267,"title":"마술을 배운 여자아이 . MANGA","writerType":"T","writer":"진히로인 텐도아카네","hits":424,"comments":6,"url":"http://bbs.ruliweb.com/community/board/300143/read/40457267?page=3","writeDt":1545790293000},{"order":242,"communityCode":"RULIWEB","bbsId":"300143","articleNo":40458710,"title":"미쳐버린 스텔라리스 근황","writerType":"T","writer":"허벅지페티쉬","hits":424,"comments":4,"url":"http://bbs.ruliweb.com/community/board/300143/read/40458710?page=1","writeDt":1545799225000},{"order":243,"communityCode":"RULIWEB","bbsId":"300143","articleNo":40460438,"title":"그런데 아저씨는 누구에요?","writerType":"T","writer":"Fluttershy♡四月一日","hits":423,"comments":8,"url":"http://bbs.ruliweb.com/community/board/300143/read/40460438?page=3","writeDt":1545809348000},{"order":244,"communityCode":"RULIWEB","bbsId":"300143","articleNo":40458210,"title":"서울 촌놈들은 모르는 대구 이월드 메가스윙 수듄;;","writerType":"T","writer":"고라파덕™","hits":423,"comments":4,"url":"http://bbs.ruliweb.com/community/board/300143/read/40458210?page=2","writeDt":1545796303000},{"order":245,"communityCode":"RULIWEB","bbsId":"300143","articleNo":40457725,"title":"[@] 딜도형 자지.jpg","writerType":"T","writer":"빌런냐옹","hits":422,"comments":3,"url":"http://bbs.ruliweb.com/community/board/300143/read/40457725?page=3","writeDt":1545793249000},{"order":246,"communityCode":"RULIWEB","bbsId":"300143","articleNo":40459616,"title":"서큐버스 신작 대기중이네.ㅋ","writerType":"T","writer":"뚫훍킹","hits":421,"comments":5,"url":"http://bbs.ruliweb.com/community/board/300143/read/40459616?page=2","writeDt":1545804650000},{"order":247,"communityCode":"RULIWEB","bbsId":"300143","articleNo":40458648,"title":"짧은 바지, 쩍벌 춤. 과도한 아이돌 성상품화 이대로 괜찮은가?","writerType":"T","writer":"Jazzzzzzzzzz","hits":420,"comments":1,"url":"http://bbs.ruliweb.com/community/board/300143/read/40458648?page=3","writeDt":1545798917000},{"order":248,"communityCode":"RULIWEB","bbsId":"300143","articleNo":40459705,"title":"신개념 굿즈.jpg","writerType":"T","writer":"부들부들™","hits":420,"comments":2,"url":"http://bbs.ruliweb.com/community/board/300143/read/40459705?page=3","writeDt":1545805085000},{"order":249,"communityCode":"RULIWEB","bbsId":"300143","articleNo":40459729,"title":"어떤 사이트의 흔하지 않은 유저의 게시글.jpg","writerType":"T","writer":"하은선혜","hits":420,"comments":11,"url":"http://bbs.ruliweb.com/community/board/300143/read/40459729?page=2","writeDt":1545805225000},{"order":250,"communityCode":"RULIWEB","bbsId":"300143","articleNo":40459796,"title":"유게이 2D 여친 클라스 수준.JPG","writerType":"T","writer":"하얀물감","hits":416,"comments":5,"url":"http://bbs.ruliweb.com/community/board/300143/read/40459796?page=3","writeDt":1545805615000},{"order":251,"communityCode":"RULIWEB","bbsId":"300143","articleNo":40459865,"title":"이순신과 거북선은 모세 같은 신화 아니냐?","writerType":"T","writer":"술담배여자","hits":416,"comments":14,"url":"http://bbs.ruliweb.com/community/board/300143/read/40459865?page=3","writeDt":1545806073000},{"order":252,"communityCode":"RULIWEB","bbsId":"300143","articleNo":40459934,"title":"모텔 샤워실 대참사 ㅋㅋㅋㅋㅋㅋㅋㅋㅋㅋㅋ","writerType":"T","writer":"아재~","hits":416,"comments":2,"url":"http://bbs.ruliweb.com/community/board/300143/read/40459934?page=1","writeDt":1545806574000},{"order":253,"communityCode":"RULIWEB","bbsId":"300143","articleNo":40457647,"title":"너 내일 전역이라며?","writerType":"T","writer":"부르마핥짝","hits":416,"comments":2,"url":"http://bbs.ruliweb.com/community/board/300143/read/40457647?page=3","writeDt":1545792711000},{"order":254,"communityCode":"RULIWEB","bbsId":"300143","articleNo":40460124,"title":"뜨개질 배운 남자가 만들어본 겨울 솜털 모자","writerType":"T","writer":"AquaStellar","hits":415,"comments":10,"url":"http://bbs.ruliweb.com/community/board/300143/read/40460124?page=2","writeDt":1545807606000},{"order":255,"communityCode":"RULIWEB","bbsId":"300143","articleNo":40460426,"title":"이해하기 어려운 포켓몬스터 상성","writerType":"T","writer":"도슬람+로리콘mk.69","hits":415,"comments":11,"url":"http://bbs.ruliweb.com/community/board/300143/read/40460426?page=3","writeDt":1545809285000},{"order":256,"communityCode":"RULIWEB","bbsId":"300143","articleNo":40457275,"title":"진화하는 수학.jpg","writerType":"T","writer":"식봉식봉이","hits":413,"comments":6,"url":"http://bbs.ruliweb.com/community/board/300143/read/40457275?page=3","writeDt":1545790383000},{"order":257,"communityCode":"RULIWEB","bbsId":"300143","articleNo":40458255,"title":"여성향 아이돌 신캐 근황","writerType":"T","writer":"치르47","hits":412,"comments":3,"url":"http://bbs.ruliweb.com/community/board/300143/read/40458255?page=1","writeDt":1545796601000},{"order":258,"communityCode":"RULIWEB","bbsId":"300143","articleNo":40460579,"title":"과거 개콘의 합법적인 치트키 ㅋㅋㅋㅋㅋㅋㅋㅋ","writerType":"T","writer":"아재~","hits":412,"comments":5,"url":"http://bbs.ruliweb.com/community/board/300143/read/40460579?page=2","writeDt":1545810173000},{"order":259,"communityCode":"RULIWEB","bbsId":"300143","articleNo":40460633,"title":"리얼리스트가 안되는 이유","writerType":"T","writer":"Rohanes","hits":412,"comments":5,"url":"http://bbs.ruliweb.com/community/board/300143/read/40460633?page=3","writeDt":1545810445000},{"order":260,"communityCode":"RULIWEB","bbsId":"300143","articleNo":40458198,"title":"왜 다들 남매 근친 픽션은 그렇게 싫어하면서","writerType":"T","writer":"마히로","hits":412,"comments":9,"url":"http://bbs.ruliweb.com/community/board/300143/read/40458198?page=3","writeDt":1545796220000},{"order":261,"communityCode":"RULIWEB","bbsId":"300143","articleNo":40459158,"title":"가상화폐 가격이 떨어진거는","writerType":"T","writer":"ZOLASSE","hits":410,"comments":3,"url":"http://bbs.ruliweb.com/community/board/300143/read/40459158?page=3","writeDt":1545801985000},{"order":262,"communityCode":"RULIWEB","bbsId":"300143","articleNo":40457913,"title":"애니플러스 애캐토 초대 우승자 ㄷㄷㄷㄷㄷㄷㄷ","writerType":"T","writer":"망동이","hits":410,"comments":4,"url":"http://bbs.ruliweb.com/community/board/300143/read/40457913?page=3","writeDt":1545794594000},{"order":263,"communityCode":"RULIWEB","bbsId":"300143","articleNo":40460312,"title":"메시???? 손흥민???? ㅋㅋㅋㅋㅋㅋ","writerType":"T","writer":"레드쥬스","hits":409,"comments":10,"url":"http://bbs.ruliweb.com/community/board/300143/read/40460312?page=3","writeDt":1545808618000},{"order":264,"communityCode":"RULIWEB","bbsId":"300143","articleNo":40460688,"title":"(R-18) 생명의 어머니.gif","writerType":"T","writer":"오르피아 똥꼬냄새","hits":409,"comments":3,"url":"http://bbs.ruliweb.com/community/board/300143/read/40460688?page=1","writeDt":1545810820000},{"order":265,"communityCode":"RULIWEB","bbsId":"300143","articleNo":40459188,"title":"처녀 vs 동정.manga","writerType":"T","writer":"철로만든댕댕이","hits":409,"comments":8,"url":"http://bbs.ruliweb.com/community/board/300143/read/40459188?page=2","writeDt":1545802173000},{"order":266,"communityCode":"RULIWEB","bbsId":"300143","articleNo":40457421,"title":"어린 시절 대꼴 여캐들.jpg","writerType":"T","writer":"쿠르스와로","hits":409,"comments":5,"url":"http://bbs.ruliweb.com/community/board/300143/read/40457421?page=1","writeDt":1545791222000},{"order":267,"communityCode":"RULIWEB","bbsId":"300143","articleNo":40457596,"title":"돌고래 로드킬 10초전.","writerType":"T","writer":"슬라네쉬숭배자","hits":408,"comments":1,"url":"http://bbs.ruliweb.com/community/board/300143/read/40457596?page=2","writeDt":1545792373000},{"order":268,"communityCode":"RULIWEB","bbsId":"300143","articleNo":40460494,"title":"빨대에는 구멍이 몇 개 있는가","writerType":"T","writer":"옴닉사태","hits":408,"comments":14,"url":"http://bbs.ruliweb.com/community/board/300143/read/40460494?page=1","writeDt":1545809620000},{"order":269,"communityCode":"RULIWEB","bbsId":"300143","articleNo":40459817,"title":"한국에 독재가 필요하고 좋아하는 애들 특징","writerType":"T","writer":"Cortana","hits":407,"comments":5,"url":"http://bbs.ruliweb.com/community/board/300143/read/40459817?page=2","writeDt":1545805754000},{"order":270,"communityCode":"RULIWEB","bbsId":"300143","articleNo":40460627,"title":"ㄹㅇ 유게에서 븅딱같은 놈 하나 보이네 ㅋㅋㅋㅋㅋㅋㅋ","writerType":"T","writer":"브더하는 시망이","hits":407,"comments":12,"url":"http://bbs.ruliweb.com/community/board/300143/read/40460627?page=3","writeDt":1545810395000},{"order":271,"communityCode":"RULIWEB","bbsId":"300143","articleNo":40457394,"title":"힐튼호텔 한국인 특별 대우 논란","writerType":"T","writer":"사라로","hits":407,"comments":3,"url":"http://bbs.ruliweb.com/community/board/300143/read/40457394?page=2","writeDt":1545791078000},{"order":272,"communityCode":"RULIWEB","bbsId":"300143","articleNo":40459262,"title":"상상과 현실.jpg","writerType":"T","writer":"虹色letters","hits":407,"comments":2,"url":"http://bbs.ruliweb.com/community/board/300143/read/40459262?page=3","writeDt":1545802569000},{"order":273,"communityCode":"RULIWEB","bbsId":"300143","articleNo":40459589,"title":"화이트메인 : 심판을... 시작한다!","writerType":"T","writer":"오르피아 똥꼬냄새","hits":406,"comments":5,"url":"http://bbs.ruliweb.com/community/board/300143/read/40459589?page=3","writeDt":1545804524000},{"order":274,"communityCode":"RULIWEB","bbsId":"300143","articleNo":40459738,"title":"퍼퍼퍼퍼퍼퍼퍼퍽 크옷 응하아아아앙❤❤❤","writerType":"T","writer":"술담배여자","hits":406,"comments":6,"url":"http://bbs.ruliweb.com/community/board/300143/read/40459738?page=2","writeDt":1545805267000},{"order":275,"communityCode":"RULIWEB","bbsId":"300143","articleNo":40457920,"title":"콘돔룩 입은 스카사하","writerType":"T","writer":"귀여운고스트","hits":405,"comments":5,"url":"http://bbs.ruliweb.com/community/board/300143/read/40457920?page=3","writeDt":1545794621000},{"order":276,"communityCode":"RULIWEB","bbsId":"300143","articleNo":40457458,"title":"[@] 사치코가 흠뻑 젖는.manga","writerType":"T","writer":"빌런냐옹","hits":405,"comments":4,"url":"http://bbs.ruliweb.com/community/board/300143/read/40457458?page=3","writeDt":1545791505000},{"order":277,"communityCode":"RULIWEB","bbsId":"300143","articleNo":40459839,"title":"열도의 흔한 물가.","writerType":"T","writer":"달빛물든","hits":404,"comments":7,"url":"http://bbs.ruliweb.com/community/board/300143/read/40459839?page=1","writeDt":1545805851000},{"order":278,"communityCode":"RULIWEB","bbsId":"300143","articleNo":40459809,"title":"위쳐3 배역 확정 났다","writerType":"T","writer":"시각을포기한다","hits":403,"comments":12,"url":"http://bbs.ruliweb.com/community/board/300143/read/40459809?page=2","writeDt":1545805684000},{"order":279,"communityCode":"RULIWEB","bbsId":"300143","articleNo":40459284,"title":"5.56mm 기관단총","writerType":"T","writer":"흑형은 큰물건","hits":402,"comments":8,"url":"http://bbs.ruliweb.com/community/board/300143/read/40459284?page=2","writeDt":1545802689000},{"order":280,"communityCode":"RULIWEB","bbsId":"300143","articleNo":40458884,"title":"2000명vs 1만5천명","writerType":"T","writer":"빵하나우유","hits":402,"comments":9,"url":"http://bbs.ruliweb.com/community/board/300143/read/40458884?page=3","writeDt":1545800290000},{"order":281,"communityCode":"RULIWEB","bbsId":"300143","articleNo":40457415,"title":"미국 친자확인 예능 레전드.JPG ㅋㅋㅋ","writerType":"T","writer":"전↗ 복↘","hits":402,"comments":7,"url":"http://bbs.ruliweb.com/community/board/300143/read/40457415?page=1","writeDt":1545791193000},{"order":282,"communityCode":"RULIWEB","bbsId":"300143","articleNo":40458786,"title":"퍼펙트 해진 기동전사 건담","writerType":"T","writer":"마시마론","hits":400,"comments":4,"url":"http://bbs.ruliweb.com/community/board/300143/read/40458786?page=3","writeDt":1545799670000},{"order":283,"communityCode":"RULIWEB","bbsId":"300143","articleNo":40459397,"title":"넷플릭스 번역 레전드","writerType":"T","writer":"반다비","hits":400,"comments":8,"url":"http://bbs.ruliweb.com/community/board/300143/read/40459397?page=2","writeDt":1545803381000},{"order":284,"communityCode":"RULIWEB","bbsId":"300143","articleNo":40457409,"title":"맛서인 레전드 나왔다","writerType":"T","writer":"혼란하다혼란해","hits":400,"comments":5,"url":"http://bbs.ruliweb.com/community/board/300143/read/40457409?page=2","writeDt":1545791148000},{"order":285,"communityCode":"RULIWEB","bbsId":"300143","articleNo":40460315,"title":"씹덕의 카톡 대참사","writerType":"T","writer":"크로오","hits":399,"comments":3,"url":"http://bbs.ruliweb.com/community/board/300143/read/40460315?page=3","writeDt":1545808637000},{"order":286,"communityCode":"RULIWEB","bbsId":"300143","articleNo":40459217,"title":"에휴 킥보드 고인물 아주.gif","writerType":"T","writer":"人生無想","hits":399,"comments":7,"url":"http://bbs.ruliweb.com/community/board/300143/read/40459217?page=1","writeDt":1545802312000},{"order":287,"communityCode":"RULIWEB","bbsId":"300143","articleNo":40457682,"title":"어머니께서 싸주신 음식 와이프가 개를 주네요.","writerType":"T","writer":"숙취에는농약공복에는소주","hits":399,"comments":16,"url":"http://bbs.ruliweb.com/community/board/300143/read/40457682?page=1","writeDt":1545792989000},{"order":288,"communityCode":"RULIWEB","bbsId":"300143","articleNo":40458207,"title":"즐거운 회식","writerType":"T","writer":"kla114","hits":399,"comments":3,"url":"http://bbs.ruliweb.com/community/board/300143/read/40458207?page=2","writeDt":1545796287000},{"order":289,"communityCode":"RULIWEB","bbsId":"300143","articleNo":40458472,"title":"한 걸그룹이 매장당한 사건","writerType":"T","writer":"ㅠㅡㅠ","hits":399,"comments":8,"url":"http://bbs.ruliweb.com/community/board/300143/read/40458472?page=3","writeDt":1545797912000},{"order":290,"communityCode":"RULIWEB","bbsId":"300143","articleNo":40460098,"title":"로마인 개그","writerType":"T","writer":"두억시니(무직)","hits":398,"comments":13,"url":"http://bbs.ruliweb.com/community/board/300143/read/40460098?page=3","writeDt":1545807470000},{"order":291,"communityCode":"RULIWEB","bbsId":"300143","articleNo":40457605,"title":"노 게임 노 라이프 작가","writerType":"T","writer":"다림","hits":398,"comments":13,"url":"http://bbs.ruliweb.com/community/board/300143/read/40457605?page=1","writeDt":1545792451000},{"order":292,"communityCode":"RULIWEB","bbsId":"300143","articleNo":40457196,"title":"시롱이에 올라탄 라이더 누님의 모습.jpg","writerType":"T","writer":"식봉식봉이","hits":398,"comments":1,"url":"http://bbs.ruliweb.com/community/board/300143/read/40457196?page=3","writeDt":1545789750000},{"order":293,"communityCode":"RULIWEB","bbsId":"300143","articleNo":40459283,"title":"[붕괴] 댓글이 답답했던 운영자","writerType":"T","writer":"테레사 아포칼립스","hits":397,"comments":7,"url":"http://bbs.ruliweb.com/community/board/300143/read/40459283?page=2","writeDt":1545802686000},{"order":294,"communityCode":"RULIWEB","bbsId":"300143","articleNo":40460136,"title":"지혜롭고 인자한 마법사 수준.jpg","writerType":"T","writer":"쾌청상승","hits":397,"comments":2,"url":"http://bbs.ruliweb.com/community/board/300143/read/40460136?page=2","writeDt":1545807705000},{"order":295,"communityCode":"RULIWEB","bbsId":"300143","articleNo":40460328,"title":"오뚜기 마요네즈 특징","writerType":"T","writer":"빨강머릿","hits":396,"comments":3,"url":"http://bbs.ruliweb.com/community/board/300143/read/40460328?page=3","writeDt":1545808692000},{"order":296,"communityCode":"RULIWEB","bbsId":"300143","articleNo":40459173,"title":"호불호 갈리는 몸매.jpg","writerType":"T","writer":"러블리즈","hits":396,"comments":5,"url":"http://bbs.ruliweb.com/community/board/300143/read/40459173?page=3","writeDt":1545802110000},{"order":297,"communityCode":"RULIWEB","bbsId":"300143","articleNo":40459201,"title":"전국 소주 대표 모델들.jpg","writerType":"T","writer":"llllllllllllll","hits":396,"comments":8,"url":"http://bbs.ruliweb.com/community/board/300143/read/40459201?page=2","writeDt":1545802241000},{"order":298,"communityCode":"RULIWEB","bbsId":"300143","articleNo":40458795,"title":"신작 3D던파가 크리티카 표절했다는 얘기 나오는 이유","writerType":"T","writer":"9784862694379","hits":395,"comments":7,"url":"http://bbs.ruliweb.com/community/board/300143/read/40458795?page=3","writeDt":1545799731000},{"order":299,"communityCode":"RULIWEB","bbsId":"300143","articleNo":40459389,"title":"전설의 붓질 .jpg","writerType":"T","writer":"하루 에스티아","hits":395,"comments":3,"url":"http://bbs.ruliweb.com/community/board/300143/read/40459389?page=2","writeDt":1545803335000},{"order":300,"communityCode":"RULIWEB","bbsId":"300143","articleNo":40457599,"title":"(히로아카)업계 포상 만화 모음.manga","writerType":"T","writer":"식봉식봉이","hits":395,"comments":5,"url":"http://bbs.ruliweb.com/community/board/300143/read/40457599?page=1","writeDt":1545792397000}]}