{"communityCode":null,"timeType":"06H","orderType":"L","articles":[{"order":1,"communityCode":"DDANZI","bbsId":"free","articleNo":544923884,"title":"로또방 신청 어케 하는지 아시는분 계신가요??","writerType":"T","writer":"*레이*","hits":14,"comments":0,"url":"http://www.ddanzi.com/free/544923884","writeDt":1547169026000},{"order":2,"communityCode":"RULIWEB","bbsId":"300143","articleNo":40670157,"title":"황당한 성폭행 사건 판결.jpg","writerType":"T","writer":"포디엠퍼러오브맨카인드","hits":113,"comments":0,"url":"http://m.ruliweb.com/community/board/300143/read/40670157","writeDt":1547169012000},{"order":3,"communityCode":"DDANZI","bbsId":"free","articleNo":544923852,"title":"파인텍 '굴뚝농성' 끝났다…노사협상 426일 만에 타결","writerType":"T","writer":"안녕하세요!","hits":25,"comments":0,"url":"http://www.ddanzi.com/free/544923852","writeDt":1547169011000},{"order":4,"communityCode":"RULIWEB","bbsId":"300143","articleNo":40670155,"title":"10억받기 vs 고자되기","writerType":"T","writer":"京極堂","hits":25,"comments":0,"url":"http://m.ruliweb.com/community/board/300143/read/40670155","writeDt":1547169011000},{"order":5,"communityCode":"RULIWEB","bbsId":"300143","articleNo":40670156,"title":"매운 요리 보면 맛있는 녀석들 보면 매운거 잘먹더라도 마라 라고 적힌 거...","writerType":"T","writer":"108638.","hits":13,"comments":0,"url":"http://m.ruliweb.com/community/board/300143/read/40670156","writeDt":1547169011000},{"order":6,"communityCode":"FMKOREA","bbsId":"humor","articleNo":1508965833,"title":"무도) 정형돈 하하 티키타카.jpg","writerType":"T","writer":"만수르구단주","hits":24,"comments":0,"url":"https://m.fmkorea.com/1508965833","writeDt":1547169000000},{"order":7,"communityCode":"RULIWEB","bbsId":"300143","articleNo":40670154,"title":"다이아방 뜻이뭐임?","writerType":"T","writer":"가람하람","hits":44,"comments":1,"url":"http://m.ruliweb.com/community/board/300143/read/40670154","writeDt":1547168997000},{"order":8,"communityCode":"RULIWEB","bbsId":"300143","articleNo":40670153,"title":"치킨이 먹고싶어요","writerType":"T","writer":"코너㈜","hits":63,"comments":1,"url":"http://m.ruliweb.com/community/board/300143/read/40670153","writeDt":1547168993000},{"order":9,"communityCode":"RULIWEB","bbsId":"300143","articleNo":40670152,"title":"유혹하는 버추얼 아이돌 gif","writerType":"T","writer":"허벅지페티쉬","hits":122,"comments":0,"url":"http://m.ruliweb.com/community/board/300143/read/40670152","writeDt":1547168991000},{"order":10,"communityCode":"RULIWEB","bbsId":"300143","articleNo":40670151,"title":"슈타게가 빼박 우익인 이유 .reason","writerType":"T","writer":"말레이B","hits":110,"comments":0,"url":"http://m.ruliweb.com/community/board/300143/read/40670151","writeDt":1547168987000},{"order":11,"communityCode":"RULIWEB","bbsId":"300143","articleNo":40670150,"title":"누가 감시자를 감시하는가?","writerType":"T","writer":"아마가미","hits":45,"comments":0,"url":"http://m.ruliweb.com/community/board/300143/read/40670150","writeDt":1547168985000},{"order":12,"communityCode":"RULIWEB","bbsId":"300143","articleNo":40670149,"title":"하리보 얘네 한국 포장 기술 배워감?","writerType":"T","writer":"lIllIl","hits":75,"comments":0,"url":"http://m.ruliweb.com/community/board/300143/read/40670149","writeDt":1547168984000},{"order":13,"communityCode":"RULIWEB","bbsId":"300143","articleNo":40670148,"title":"강형욱 어릴적 사진.","writerType":"T","writer":"루리웹-1968637897","hits":88,"comments":0,"url":"http://m.ruliweb.com/community/board/300143/read/40670148","writeDt":1547168982000},{"order":14,"communityCode":"DDANZI","bbsId":"free","articleNo":544923774,"title":"보유주식 97프로 감자...투자비 3프로 남았네요","writerType":"T","writer":"초허접님","hits":60,"comments":0,"url":"http://www.ddanzi.com/free/544923774","writeDt":1547168978000},{"order":15,"communityCode":"DDANZI","bbsId":"free","articleNo":544923749,"title":"지금 우리나라에 진보는 없습니다","writerType":"T","writer":"더불어2D당대표","hits":44,"comments":0,"url":"http://www.ddanzi.com/free/544923749","writeDt":1547168972000},{"order":16,"communityCode":"DDANZI","bbsId":"free","articleNo":544923757,"title":"혹시 안네 발렌틴 안경 쓰시는분 계신가요??","writerType":"T","writer":"씨뻘교황","hits":20,"comments":1,"url":"http://www.ddanzi.com/free/544923757","writeDt":1547168972000},{"order":17,"communityCode":"RULIWEB","bbsId":"300143","articleNo":40670147,"title":"군 면제받기 VS 고자 되고 현역 가기","writerType":"T","writer":"쳐웃지마라","hits":99,"comments":7,"url":"http://m.ruliweb.com/community/board/300143/read/40670147","writeDt":1547168957000},{"order":18,"communityCode":"HUMORUNIV","bbsId":"pdswait","articleNo":6636130,"title":"꺼토미히라주의) 이런 화풍 작가 추천좀","writerType":"T","writer":"자나깨나발기조심","hits":7,"comments":0,"url":"http://m.humoruniv.com/board/read.html?table=pdswait&number=6636130","writeDt":1547168956000},{"order":19,"communityCode":"HUMORUNIV","bbsId":"pdswait","articleNo":6636131,"title":"꺼토미히라주의) 이런 화풍 작가 추천좀","writerType":"T","writer":"자나깨나발기조심","hits":17,"comments":0,"url":"http://m.humoruniv.com/board/read.html?table=pdswait&number=6636131","writeDt":1547168956000},{"order":20,"communityCode":"RULIWEB","bbsId":"300143","articleNo":40670146,"title":"몬헌 월드 방어구 알파 베타 있잖아","writerType":"T","writer":"DDOG","hits":70,"comments":4,"url":"http://m.ruliweb.com/community/board/300143/read/40670146","writeDt":1547168949000},{"order":21,"communityCode":"SLRCLUB","bbsId":"free","articleNo":36850945,"title":"m.2 ssd 고정나사 ㄷㄷㄷ","writerType":"T","writer":"아푸리카청춘이다","hits":4,"comments":0,"url":"http://m.slrclub.com/v/free/36850945","writeDt":1547168947000},{"order":22,"communityCode":"SLRCLUB","bbsId":"free","articleNo":36850944,"title":"스타워즈 스핀오프 도 스토리 연계되는건가요?","writerType":"T","writer":"닑네임","hits":2,"comments":0,"url":"http://m.slrclub.com/v/free/36850944","writeDt":1547168945000},{"order":23,"communityCode":"SLRCLUB","bbsId":"free","articleNo":36850943,"title":"이 샴푸 어때요?","writerType":"T","writer":"일요일","hits":21,"comments":0,"url":"http://m.slrclub.com/v/free/36850943","writeDt":1547168944000},{"order":24,"communityCode":"DDANZI","bbsId":"free","articleNo":544923626,"title":"상당히 아스트랄한 놀이기구 ㄷㄷㄷ","writerType":"T","writer":"일격살충","hits":150,"comments":0,"url":"http://www.ddanzi.com/free/544923626","writeDt":1547168943000},{"order":25,"communityCode":"FMKOREA","bbsId":"humor","articleNo":1513469495,"title":"황당한 성폭행 사건 판결.jpg","writerType":"T","writer":"얍얍오오예얍얍","hits":172,"comments":0,"url":"https://m.fmkorea.com/1513469495","writeDt":1547168940000},{"order":26,"communityCode":"FMKOREA","bbsId":"humor","articleNo":1513471587,"title":"북극에서 일출 일몰 ㄷㄷㄷ","writerType":"T","writer":"으엑","hits":33,"comments":0,"url":"https://m.fmkorea.com/1513471587","writeDt":1547168940000},{"order":27,"communityCode":"FMKOREA","bbsId":"humor","articleNo":1513472110,"title":"2부리그 시절 레스터 벤치.jpg","writerType":"T","writer":"유이가하마유이","hits":134,"comments":0,"url":"https://m.fmkorea.com/1513472110","writeDt":1547168940000},{"order":28,"communityCode":"MLBPARK","bbsId":"bullpen","articleNo":201901110026950208,"title":"배우 키키 키린의 마지막 인사, 그만 울컥해버렸다","writerType":"T","writer":"이글스홈런","hits":23,"comments":0,"url":"http://mlbpark.donga.com/mp/b.php?p=1&b=bullpen&id=201901110026950208&site=donga.com","writeDt":1547168940000},{"order":29,"communityCode":"MLBPARK","bbsId":"bullpen","articleNo":201901110026950211,"title":"삼국지) 노숙은 평가 좋은 편인가요? 별로인편인가요?","writerType":"T","writer":"그패봐봐","hits":15,"comments":0,"url":"http://mlbpark.donga.com/mp/b.php?p=1&b=bullpen&id=201901110026950211&site=donga.com","writeDt":1547168940000},{"order":30,"communityCode":"BOBAEDREAM","bbsId":"strange","articleNo":2732071,"title":"서울대 축제현장.jpg","writerType":"T","writer":"판검사대신용사..","hits":80,"comments":0,"url":"http://m.bobaedream.co.kr/board/bbs_view/strange/2732071","writeDt":1547168940000},{"order":31,"communityCode":"DDANZI","bbsId":"free","articleNo":544923680,"title":"주간업무보고 쓰려고 보니, 이번주에 진짜 한게 없네여 ㄷㄷㄷㄷㄷ","writerType":"T","writer":"ㅎㄷㄷㄷ","hits":33,"comments":1,"url":"http://www.ddanzi.com/free/544923680","writeDt":1547168937000},{"order":32,"communityCode":"RULIWEB","bbsId":"300143","articleNo":40670145,"title":"아 똥마렵다 방금 동 싸고 나왔는데","writerType":"T","writer":"무커아들무케","hits":53,"comments":4,"url":"http://m.ruliweb.com/community/board/300143/read/40670145","writeDt":1547168936000},{"order":33,"communityCode":"COOK82","bbsId":"15","articleNo":2701053,"title":"굳이 요리커뮤니티에 들어오는 남자들의 심리","writerType":"T","writer":"..","hits":5,"comments":0,"url":"http://www.82cook.com/entiz/read.php?bn=15&num=2701053","writeDt":1547168924000},{"order":34,"communityCode":"RULIWEB","bbsId":"300143","articleNo":40670144,"title":"드디어 본성을 드러내는 버추얼 아이돌.jpg","writerType":"T","writer":"아마가미","hits":316,"comments":1,"url":"http://m.ruliweb.com/community/board/300143/read/40670144","writeDt":1547168922000},{"order":35,"communityCode":"RULIWEB","bbsId":"300143","articleNo":40670143,"title":"(아래꼬리)프리스크vs머팻","writerType":"T","writer":"망자덮밥","hits":95,"comments":1,"url":"http://m.ruliweb.com/community/board/300143/read/40670143","writeDt":1547168920000},{"order":36,"communityCode":"PPOMPPU","bbsId":"freeboard","articleNo":6234357,"title":"한국갤럽 문통 지지도 3%상승","writerType":"T","writer":"인정작군","hits":30,"comments":0,"url":"http://m.ppomppu.co.kr/new/bbs_view.php?id=freeboard&no=6234357","writeDt":1547168907000},{"order":37,"communityCode":"RULIWEB","bbsId":"300143","articleNo":40670142,"title":"와우 똥꼬충이 뭔이야기여?","writerType":"T","writer":"우걱우걱쫩쫩","hits":97,"comments":7,"url":"http://m.ruliweb.com/community/board/300143/read/40670142","writeDt":1547168904000},{"order":38,"communityCode":"PPOMPPU","bbsId":"freeboard","articleNo":6234356,"title":"나까무라 쿄우노 \"양승태 검찰소환, 문재인정부 사법장악 시도가 사법난국으로 치달아\"","writerType":"T","writer":"캬뷰","hits":39,"comments":1,"url":"http://m.ppomppu.co.kr/new/bbs_view.php?id=freeboard&no=6234356","writeDt":1547168903000},{"order":39,"communityCode":"DDANZI","bbsId":"free","articleNo":544923615,"title":"덱스터, CJ E&M과 합병 ㄷㄷㄷ","writerType":"T","writer":"mz3","hits":114,"comments":0,"url":"http://www.ddanzi.com/free/544923615","writeDt":1547168899000},{"order":40,"communityCode":"PPOMPPU","bbsId":"freeboard","articleNo":6234355,"title":"설날 8박 10일로 베트남 항공권 결제 완료","writerType":"T","writer":"병형신이야","hits":82,"comments":2,"url":"http://m.ppomppu.co.kr/new/bbs_view.php?id=freeboard&no=6234355","writeDt":1547168892000},{"order":41,"communityCode":"RULIWEB","bbsId":"300143","articleNo":40670141,"title":"(히로아카)다음은... 너다!","writerType":"T","writer":"아마가미","hits":240,"comments":0,"url":"http://m.ruliweb.com/community/board/300143/read/40670141","writeDt":1547168885000},{"order":42,"communityCode":"MLBPARK","bbsId":"bullpen","articleNo":201901110026950193,"title":"성폭행 사태로 난리가 났는데 진실공방이라... 뭐 이 참에 다 조사하면 되죠.","writerType":"T","writer":"lowend","hits":110,"comments":0,"url":"http://mlbpark.donga.com/mp/b.php?p=1&b=bullpen&id=201901110026950193&site=donga.com","writeDt":1547168880000},{"order":43,"communityCode":"MLBPARK","bbsId":"bullpen","articleNo":201901110026950196,"title":"전라북도 전주 추억의 만남의 장소.jpg","writerType":"T","writer":"spinner","hits":191,"comments":2,"url":"http://mlbpark.donga.com/mp/b.php?p=1&b=bullpen&id=201901110026950196&site=donga.com","writeDt":1547168880000},{"order":44,"communityCode":"MLBPARK","bbsId":"bullpen","articleNo":201901110026950199,"title":"지금 생각해보면 학교에서 대체 왜 하는건지 1도 이해 안가는거","writerType":"T","writer":"vGuerrero","hits":66,"comments":2,"url":"http://mlbpark.donga.com/mp/b.php?p=1&b=bullpen&id=201901110026950199&site=donga.com","writeDt":1547168880000},{"order":45,"communityCode":"MLBPARK","bbsId":"bullpen","articleNo":201901110026950202,"title":"[아이즈원] 사쿠라 하루 사이의 갭.jpg","writerType":"T","writer":"머룬","hits":103,"comments":0,"url":"http://mlbpark.donga.com/mp/b.php?p=1&b=bullpen&id=201901110026950202&site=donga.com","writeDt":1547168880000},{"order":46,"communityCode":"MLBPARK","bbsId":"bullpen","articleNo":201901110026950205,"title":"런닝머신 멀미 적응하려면 어떡해야하나요?","writerType":"T","writer":"박준혁","hits":8,"comments":0,"url":"http://mlbpark.donga.com/mp/b.php?p=1&b=bullpen&id=201901110026950205&site=donga.com","writeDt":1547168880000},{"order":47,"communityCode":"DDANZI","bbsId":"free","articleNo":544923332,"title":"초코에몽은 남양유업 껍니다","writerType":"T","writer":"0123456789","hits":97,"comments":8,"url":"http://www.ddanzi.com/free/544923332","writeDt":1547168871000},{"order":48,"communityCode":"DDANZI","bbsId":"free","articleNo":544923552,"title":"사주 무료로 보는 사이트 혹시 아시는분 있나요 ?ㅠㅠ","writerType":"T","writer":"약드실시간입니다","hits":17,"comments":2,"url":"http://www.ddanzi.com/free/544923552","writeDt":1547168870000},{"order":49,"communityCode":"DVDPRIME","bbsId":"comm","articleNo":19678797,"title":"트럼프의 셧다운 버티기를 보면서 느끼는 잡담","writerType":"T","writer":"賣香人","hits":86,"comments":1,"url":"https://dvdprime.com/g2/bbs/board.php?bo_table=comm&wr_id=19678797","writeDt":1547168868000},{"order":50,"communityCode":"RULIWEB","bbsId":"300143","articleNo":40670140,"title":"12월 26일 배란 했으면 오늘 생리 시작하는게 맞는거냐?","writerType":"T","writer":"spaceofsoul","hits":203,"comments":12,"url":"http://m.ruliweb.com/community/board/300143/read/40670140","writeDt":1547168859000},{"order":51,"communityCode":"RULIWEB","bbsId":"300143","articleNo":40670139,"title":"댓글 알림 창 바꼈네 ㅅㅂ","writerType":"T","writer":"Sharon","hits":51,"comments":0,"url":"http://m.ruliweb.com/community/board/300143/read/40670139","writeDt":1547168855000},{"order":52,"communityCode":"RULIWEB","bbsId":"300143","articleNo":40670137,"title":"알람메세지 뷰웅신 같이 바꾼거 뭐냐","writerType":"T","writer":"서유혼","hits":49,"comments":0,"url":"http://m.ruliweb.com/community/board/300143/read/40670137","writeDt":1547168854000},{"order":53,"communityCode":"RULIWEB","bbsId":"300143","articleNo":40670138,"title":"페그오) 이건 스토리 몇장이 재미있음?","writerType":"T","writer":"와!","hits":50,"comments":6,"url":"http://m.ruliweb.com/community/board/300143/read/40670138","writeDt":1547168854000},{"order":54,"communityCode":"CLIEN","bbsId":"park","articleNo":13040171,"title":"도요타, 다카타 에어백 장착 북미 차량 170만대 리콜","writerType":"T","writer":"fiat","hits":108,"comments":0,"url":"https://m.clien.net/service/board/park/13040171","writeDt":1547168853000},{"order":55,"communityCode":"DDANZI","bbsId":"free","articleNo":544923495,"title":"자동차배터리 자가교체 했습니다(Feat. 오픈마켓 바가지)","writerType":"T","writer":"독거공노비","hits":85,"comments":2,"url":"http://www.ddanzi.com/free/544923495","writeDt":1547168846000},{"order":56,"communityCode":"SLRCLUB","bbsId":"free","articleNo":36850942,"title":"천만원 넘게 버는 남자들은 여자만날때 이런거 다 자랑하고 그러나요?","writerType":"T","writer":"유구무언","hits":81,"comments":5,"url":"http://m.slrclub.com/v/free/36850942","writeDt":1547168845000},{"order":57,"communityCode":"RULIWEB","bbsId":"300143","articleNo":40670136,"title":"난 군대갔다오니깐","writerType":"T","writer":"루시의상실","hits":63,"comments":5,"url":"http://m.ruliweb.com/community/board/300143/read/40670136","writeDt":1547168833000},{"order":58,"communityCode":"RULIWEB","bbsId":"300143","articleNo":40670135,"title":"사실 와우 군단까지 했으면 워크래프트 사가까지는 다 한거","writerType":"T","writer":"마르군","hits":63,"comments":0,"url":"http://m.ruliweb.com/community/board/300143/read/40670135","writeDt":1547168826000},{"order":59,"communityCode":"INVEN","bbsId":"2097","articleNo":1132937,"title":"걸그룹 게임단 아쿠아 윤해솔 (데이터 주..","writerType":"T","writer":"Ecstasis","hits":145,"comments":1,"url":"http://m.inven.co.kr/board/powerbbs.php?come_idx=2097&l=1132937","writeDt":1547168820000},{"order":60,"communityCode":"FMKOREA","bbsId":"humor","articleNo":1513470024,"title":"근데 펨코궁금한게 군대 빼면 뺴는게 좋다이러면서","writerType":"T","writer":"발로차는싸커","hits":72,"comments":9,"url":"https://m.fmkorea.com/1513470024","writeDt":1547168820000},{"order":61,"communityCode":"MLBPARK","bbsId":"bullpen","articleNo":201901110026950160,"title":"1993년 인기 가수들 집합.jpg","writerType":"T","writer":"임창정","hits":187,"comments":5,"url":"http://mlbpark.donga.com/mp/b.php?p=1&b=bullpen&id=201901110026950160&site=donga.com","writeDt":1547168820000},{"order":62,"communityCode":"MLBPARK","bbsId":"bullpen","articleNo":201901110026950163,"title":"'유아' 하면 누구부터 생각 나시나요?","writerType":"T","writer":"미르피티","hits":236,"comments":16,"url":"http://mlbpark.donga.com/mp/b.php?p=1&b=bullpen&id=201901110026950163&site=donga.com","writeDt":1547168820000},{"order":63,"communityCode":"MLBPARK","bbsId":"bullpen","articleNo":201901110026950166,"title":"법이 바껴서 특근비 올랐네요","writerType":"T","writer":"27XX이기자","hits":63,"comments":0,"url":"http://mlbpark.donga.com/mp/b.php?p=1&b=bullpen&id=201901110026950166&site=donga.com","writeDt":1547168820000},{"order":64,"communityCode":"MLBPARK","bbsId":"bullpen","articleNo":201901110026950169,"title":"김태리 조성희감독 신작 들어가네요","writerType":"T","writer":"estella","hits":79,"comments":0,"url":"http://mlbpark.donga.com/mp/b.php?p=1&b=bullpen&id=201901110026950169&site=donga.com","writeDt":1547168820000},{"order":65,"communityCode":"MLBPARK","bbsId":"bullpen","articleNo":201901110026950172,"title":"부평 대한극장? 시설이 어떤가요?","writerType":"T","writer":"九州物語","hits":37,"comments":3,"url":"http://mlbpark.donga.com/mp/b.php?p=1&b=bullpen&id=201901110026950172&site=donga.com","writeDt":1547168820000},{"order":66,"communityCode":"MLBPARK","bbsId":"bullpen","articleNo":201901110026950175,"title":"천안에 맛집있나요??","writerType":"T","writer":"박보검","hits":40,"comments":2,"url":"http://mlbpark.donga.com/mp/b.php?p=1&b=bullpen&id=201901110026950175&site=donga.com","writeDt":1547168820000},{"order":67,"communityCode":"MLBPARK","bbsId":"bullpen","articleNo":201901110026950178,"title":"[nba] 보스턴 최근 상승세여서 기사도 올라왔는데..","writerType":"T","writer":"ID/PWD찾기","hits":62,"comments":1,"url":"http://mlbpark.donga.com/mp/b.php?p=1&b=bullpen&id=201901110026950178&site=donga.com","writeDt":1547168820000},{"order":68,"communityCode":"MLBPARK","bbsId":"bullpen","articleNo":201901110026950181,"title":"만남의 장소로 종로 버거킹은 왜 안나오나요","writerType":"T","writer":"겜오버","hits":48,"comments":2,"url":"http://mlbpark.donga.com/mp/b.php?p=1&b=bullpen&id=201901110026950181&site=donga.com","writeDt":1547168820000},{"order":69,"communityCode":"MLBPARK","bbsId":"bullpen","articleNo":201901110026950184,"title":"김보름건 밥데용코치 인터뷰도","writerType":"T","writer":"종달새비상","hits":255,"comments":1,"url":"http://mlbpark.donga.com/mp/b.php?p=1&b=bullpen&id=201901110026950184&site=donga.com","writeDt":1547168820000},{"order":70,"communityCode":"MLBPARK","bbsId":"bullpen","articleNo":201901110026950187,"title":"갤럽 대통령 지지율 48%로 반등","writerType":"T","writer":"게보린","hits":233,"comments":0,"url":"http://mlbpark.donga.com/mp/b.php?p=1&b=bullpen&id=201901110026950187&site=donga.com","writeDt":1547168820000},{"order":71,"communityCode":"MLBPARK","bbsId":"bullpen","articleNo":201901110026950190,"title":"엠씨더맥스 콘서트 처음 갔다왔는데 정말 좋았네요","writerType":"T","writer":"정직한사람","hits":61,"comments":0,"url":"http://mlbpark.donga.com/mp/b.php?p=1&b=bullpen&id=201901110026950190&site=donga.com","writeDt":1547168820000},{"order":72,"communityCode":"BOBAEDREAM","bbsId":"freeb","articleNo":1552108,"title":"여자한테 밥사주는거 아까운건 싫어서죠?","writerType":"T","writer":"허리아픈계절인","hits":15,"comments":0,"url":"http://m.bobaedream.co.kr/board/bbs_view/freeb/1552108","writeDt":1547168820000},{"order":73,"communityCode":"BOBAEDREAM","bbsId":"strange","articleNo":2732070,"title":"어떻게 하면 좋을까요?","writerType":"T","writer":"20년째초보운..","hits":331,"comments":5,"url":"http://m.bobaedream.co.kr/board/bbs_view/strange/2732070","writeDt":1547168820000},{"order":74,"communityCode":"COOK82","bbsId":"15","articleNo":2701052,"title":"연애의 맛 김정훈","writerType":"T","writer":"국수먹나요?..","hits":91,"comments":0,"url":"http://www.82cook.com/entiz/read.php?bn=15&num=2701052","writeDt":1547168816000},{"order":75,"communityCode":"RULIWEB","bbsId":"300143","articleNo":40670134,"title":"친구를 배려해주는 착한 지로쨩","writerType":"T","writer":"아마가미","hits":191,"comments":1,"url":"http://m.ruliweb.com/community/board/300143/read/40670134","writeDt":1547168814000},{"order":76,"communityCode":"SLRCLUB","bbsId":"free","articleNo":36850941,"title":"결혼8년차 8살5살 와이프가 개선의지가없어용","writerType":"T","writer":"유리멘탈애둘아빠","hits":118,"comments":1,"url":"http://m.slrclub.com/v/free/36850941","writeDt":1547168814000},{"order":77,"communityCode":"SLRCLUB","bbsId":"free","articleNo":36850940,"title":"노트10 궁굼궁굼","writerType":"T","writer":"악녀를보았다","hits":16,"comments":0,"url":"http://m.slrclub.com/v/free/36850940","writeDt":1547168813000},{"order":78,"communityCode":"RULIWEB","bbsId":"300143","articleNo":40670133,"title":"유리핥기","writerType":"T","writer":"빗치","hits":128,"comments":0,"url":"http://m.ruliweb.com/community/board/300143/read/40670133","writeDt":1547168812000},{"order":79,"communityCode":"RULIWEB","bbsId":"300143","articleNo":40670132,"title":"니들은 키배뜨지마라","writerType":"T","writer":"진리는 라면","hits":148,"comments":3,"url":"http://m.ruliweb.com/community/board/300143/read/40670132","writeDt":1547168807000},{"order":80,"communityCode":"RULIWEB","bbsId":"300143","articleNo":40670131,"title":"열도 아이돌 ㄱㄱ미수 사건 근황","writerType":"T","writer":"빠꼬","hits":471,"comments":9,"url":"http://m.ruliweb.com/community/board/300143/read/40670131","writeDt":1547168804000},{"order":81,"communityCode":"RULIWEB","bbsId":"300143","articleNo":40670130,"title":"강호동이 종합격투기도 했으면 어땠을까","writerType":"T","writer":"l83kd7qk","hits":95,"comments":3,"url":"http://m.ruliweb.com/community/board/300143/read/40670130","writeDt":1547168800000},{"order":82,"communityCode":"RULIWEB","bbsId":"300143","articleNo":40670129,"title":"아 학교 급 짜증나진다","writerType":"T","writer":"楯山文乃","hits":56,"comments":3,"url":"http://m.ruliweb.com/community/board/300143/read/40670129","writeDt":1547168789000},{"order":83,"communityCode":"RULIWEB","bbsId":"300143","articleNo":40670128,"title":"쿨러 안 켰다고 씨퓨가 60도를 찍네","writerType":"T","writer":"고장난전축","hits":121,"comments":8,"url":"http://m.ruliweb.com/community/board/300143/read/40670128","writeDt":1547168788000},{"order":84,"communityCode":"PPOMPPU","bbsId":"freeboard","articleNo":6234354,"title":"갤럽도 상승","writerType":"T","writer":"컷패스트","hits":85,"comments":0,"url":"http://m.ppomppu.co.kr/new/bbs_view.php?id=freeboard&no=6234354","writeDt":1547168782000},{"order":85,"communityCode":"PPOMPPU","bbsId":"freeboard","articleNo":6234353,"title":"이 정도면 누가 일부러 긁어놓은거 아닌가요","writerType":"T","writer":"빵이아빠","hits":406,"comments":25,"url":"http://m.ppomppu.co.kr/new/bbs_view.php?id=freeboard&no=6234353","writeDt":1547168765000},{"order":86,"communityCode":"CLIEN","bbsId":"park","articleNo":13040167,"title":"드뎌 연말에 딸래미때문에 가요대제전이랑 마마를 강제시청해서 BTS멤버 다외웠습니다","writerType":"T","writer":"바오","hits":188,"comments":1,"url":"https://m.clien.net/service/board/park/13040167","writeDt":1547168763000},{"order":87,"communityCode":"DDANZI","bbsId":"free","articleNo":544923209,"title":"이거 누군지 아시는분 계신가요? av 배우 같은데.","writerType":"T","writer":"모쿠마","hits":199,"comments":5,"url":"http://www.ddanzi.com/free/544923209","writeDt":1547168762000},{"order":88,"communityCode":"MLBPARK","bbsId":"bullpen","articleNo":201901110026950157,"title":"비타민D 는 어느제품이 좋은가요?","writerType":"T","writer":"September9","hits":90,"comments":5,"url":"http://mlbpark.donga.com/mp/b.php?p=1&b=bullpen&id=201901110026950157&site=donga.com","writeDt":1547168760000},{"order":89,"communityCode":"BOBAEDREAM","bbsId":"freeb","articleNo":1552107,"title":"경차 세차하기 엄청편하네요","writerType":"T","writer":"spe02","hits":23,"comments":0,"url":"http://m.bobaedream.co.kr/board/bbs_view/freeb/1552107","writeDt":1547168760000},{"order":90,"communityCode":"BOBAEDREAM","bbsId":"strange","articleNo":2732069,"title":"20대 남성지지도? 그거 그냥 무시해도 됩니다.","writerType":"T","writer":"18MB","hits":246,"comments":6,"url":"http://m.bobaedream.co.kr/board/bbs_view/strange/2732069","writeDt":1547168760000},{"order":91,"communityCode":"HUMORUNIV","bbsId":"pdswait","articleNo":6636129,"title":"노래방 근황 .jpg","writerType":"T","writer":"다비이이이","hits":71,"comments":0,"url":"http://m.humoruniv.com/board/read.html?table=pdswait&number=6636129","writeDt":1547168756000},{"order":92,"communityCode":"RULIWEB","bbsId":"300143","articleNo":40670126,"title":"발랄라이카 누님의 어린시절.jpg","writerType":"T","writer":"아마가미","hits":541,"comments":3,"url":"http://m.ruliweb.com/community/board/300143/read/40670126","writeDt":1547168755000},{"order":93,"communityCode":"RULIWEB","bbsId":"300143","articleNo":40670125,"title":"이상하게 염소고기 먹으면 쾌변?하더라","writerType":"T","writer":"뾰족머리삼돌이","hits":100,"comments":10,"url":"http://m.ruliweb.com/community/board/300143/read/40670125","writeDt":1547168749000},{"order":94,"communityCode":"SLRCLUB","bbsId":"free","articleNo":36850939,"title":"와이프는 주부인데 사업자등록을 내면 건강보험을 따로 내야하는가요?","writerType":"T","writer":"짜짜게이","hits":63,"comments":5,"url":"http://m.slrclub.com/v/free/36850939","writeDt":1547168747000},{"order":95,"communityCode":"RULIWEB","bbsId":"300143","articleNo":40670123,"title":"데스티니 가디언즈 할만하냐","writerType":"T","writer":"채찍여왕","hits":147,"comments":8,"url":"http://m.ruliweb.com/community/board/300143/read/40670123","writeDt":1547168743000},{"order":96,"communityCode":"RULIWEB","bbsId":"300143","articleNo":40670124,"title":"유흥업소가 돈 많이 깨지지?","writerType":"T","writer":"이사령","hits":317,"comments":11,"url":"http://m.ruliweb.com/community/board/300143/read/40670124","writeDt":1547168743000},{"order":97,"communityCode":"RULIWEB","bbsId":"300143","articleNo":40670122,"title":"쓉덕 폰케이스","writerType":"T","writer":"딥스펙터","hits":167,"comments":2,"url":"http://m.ruliweb.com/community/board/300143/read/40670122","writeDt":1547168741000},{"order":98,"communityCode":"RULIWEB","bbsId":"300143","articleNo":40670121,"title":"인바디검사를 하고 말야","writerType":"T","writer":"Lorikov_Quest","hits":102,"comments":1,"url":"http://m.ruliweb.com/community/board/300143/read/40670121","writeDt":1547168736000},{"order":99,"communityCode":"PPOMPPU","bbsId":"freeboard","articleNo":6234352,"title":"옥션 CGV성공!","writerType":"T","writer":"li0il0","hits":208,"comments":3,"url":"http://m.ppomppu.co.kr/new/bbs_view.php?id=freeboard&no=6234352","writeDt":1547168734000},{"order":100,"communityCode":"DDANZI","bbsId":"free","articleNo":544923049,"title":"공랭 CPU 쿨러 덩치, 승부 받습니다!","writerType":"T","writer":"chobo_","hits":155,"comments":5,"url":"http://www.ddanzi.com/free/544923049","writeDt":1547168732000},{"order":101,"communityCode":"CLIEN","bbsId":"park","articleNo":13040164,"title":"도시 어부를 보고 있는데..","writerType":"T","writer":"하나돌","hits":429,"comments":3,"url":"https://m.clien.net/service/board/park/13040164","writeDt":1547168731000},{"order":102,"communityCode":"RULIWEB","bbsId":"300143","articleNo":40670120,"title":"5등분 애니 퀄리티 무엇","writerType":"T","writer":"13살무녀에요","hits":296,"comments":5,"url":"http://m.ruliweb.com/community/board/300143/read/40670120","writeDt":1547168728000},{"order":103,"communityCode":"DDANZI","bbsId":"free","articleNo":544923159,"title":"엉덩이 마우스패드류 레어템 ㄷㄷㄷ","writerType":"T","writer":"일격살충","hits":196,"comments":1,"url":"http://www.ddanzi.com/free/544923159","writeDt":1547168727000},{"order":104,"communityCode":"RULIWEB","bbsId":"300143","articleNo":40670119,"title":"프로필 상태메시지의 중요성","writerType":"T","writer":"미쿠생태학","hits":249,"comments":1,"url":"http://m.ruliweb.com/community/board/300143/read/40670119","writeDt":1547168721000},{"order":105,"communityCode":"RULIWEB","bbsId":"300143","articleNo":40670118,"title":"국방부 소속 사쿠라.jpg","writerType":"T","writer":"아마가미","hits":456,"comments":5,"url":"http://m.ruliweb.com/community/board/300143/read/40670118","writeDt":1547168717000},{"order":106,"communityCode":"RULIWEB","bbsId":"300143","articleNo":40670117,"title":"헤이세이 라이더 1기 2기 인기캐특","writerType":"T","writer":"AtlacNcha","hits":148,"comments":4,"url":"http://m.ruliweb.com/community/board/300143/read/40670117","writeDt":1547168704000},{"order":107,"communityCode":"INVEN","bbsId":"2097","articleNo":1132936,"title":"좆소기업입사할때 마음가짐이 중요함","writerType":"T","writer":"Equinoxx","hits":347,"comments":3,"url":"http://m.inven.co.kr/board/powerbbs.php?come_idx=2097&l=1132936","writeDt":1547168700000},{"order":108,"communityCode":"FMKOREA","bbsId":"humor","articleNo":1513463554,"title":"브런치에서 버팔로 미친놈 발견","writerType":"T","writer":"에스프레소주","hits":210,"comments":1,"url":"https://m.fmkorea.com/1513463554","writeDt":1547168700000},{"order":109,"communityCode":"MLBPARK","bbsId":"bullpen","articleNo":201901110026950145,"title":"일본은 정말 한국에 관심이 장난 아니네요","writerType":"T","writer":"홀더도어","hits":367,"comments":10,"url":"http://mlbpark.donga.com/mp/b.php?p=1&b=bullpen&id=201901110026950145&site=donga.com","writeDt":1547168700000},{"order":110,"communityCode":"MLBPARK","bbsId":"bullpen","articleNo":201901110026950148,"title":"직원 뽑고 있어서 구직 싸이트에 공고 싹 올렸는데","writerType":"T","writer":"몬스터시즌","hits":361,"comments":12,"url":"http://mlbpark.donga.com/mp/b.php?p=1&b=bullpen&id=201901110026950148&site=donga.com","writeDt":1547168700000},{"order":111,"communityCode":"MLBPARK","bbsId":"bullpen","articleNo":201901110026950151,"title":"[고전] 삼국지 오나라 총사령관들","writerType":"T","writer":"[엄백호]","hits":262,"comments":5,"url":"http://mlbpark.donga.com/mp/b.php?p=1&b=bullpen&id=201901110026950151&site=donga.com","writeDt":1547168700000},{"order":112,"communityCode":"MLBPARK","bbsId":"bullpen","articleNo":201901110026950139,"title":"도서관에서 정각때마다 시간 소리나게해두는 사람 있는데요","writerType":"T","writer":"동물말머리","hits":149,"comments":7,"url":"http://mlbpark.donga.com/mp/b.php?p=1&b=bullpen&id=201901110026950139&site=donga.com","writeDt":1547168700000},{"order":113,"communityCode":"MLBPARK","bbsId":"bullpen","articleNo":201901110026950142,"title":"신작영화 자전차왕 엄복동 시나리오 예상","writerType":"T","writer":"한조만해요","hits":87,"comments":0,"url":"http://mlbpark.donga.com/mp/b.php?p=1&b=bullpen&id=201901110026950142&site=donga.com","writeDt":1547168700000},{"order":114,"communityCode":"BOBAEDREAM","bbsId":"strange","articleNo":2732068,"title":"펌)세계1위선수의 용기!!","writerType":"T","writer":"똥꼬따가워7","hits":482,"comments":0,"url":"http://m.bobaedream.co.kr/board/bbs_view/strange/2732068","writeDt":1547168700000},{"order":115,"communityCode":"SLRCLUB","bbsId":"free","articleNo":36850938,"title":"최근에 달러 환전해보신 자게이 계신가유?","writerType":"T","writer":"만1","hits":62,"comments":1,"url":"http://m.slrclub.com/v/free/36850938","writeDt":1547168698000},{"order":116,"communityCode":"RULIWEB","bbsId":"300143","articleNo":40670116,"title":"아쿠아와 메구밍 manhwa.","writerType":"T","writer":"망자덮밥","hits":422,"comments":7,"url":"http://m.ruliweb.com/community/board/300143/read/40670116","writeDt":1547168696000},{"order":117,"communityCode":"SLRCLUB","bbsId":"free","articleNo":36850937,"title":"샤오미 노트7 발표","writerType":"T","writer":"위도우메이커♥","hits":245,"comments":6,"url":"http://m.slrclub.com/v/free/36850937","writeDt":1547168690000},{"order":118,"communityCode":"COOK82","bbsId":"15","articleNo":2701051,"title":"제가 잘못 행동한 걸까요 ?","writerType":"T","writer":"봄이오면","hits":116,"comments":4,"url":"http://www.82cook.com/entiz/read.php?bn=15&num=2701051","writeDt":1547168689000},{"order":119,"communityCode":"CLIEN","bbsId":"park","articleNo":13040162,"title":"김예령 기자에게 애써 최대한 부드럽게 순화해서 말씀드리고 싶네요","writerType":"T","writer":"ASURA","hits":415,"comments":2,"url":"https://m.clien.net/service/board/park/13040162","writeDt":1547168688000},{"order":120,"communityCode":"CLIEN","bbsId":"park","articleNo":13040161,"title":"마루마루등 불법 만화사이트가 망한건 좋은 일이지만...","writerType":"T","writer":"MR.SOPHUS","hits":461,"comments":5,"url":"https://m.clien.net/service/board/park/13040161","writeDt":1547168687000},{"order":121,"communityCode":"RULIWEB","bbsId":"300143","articleNo":40670115,"title":"두 유게 가장 큰 차이는","writerType":"T","writer":"MRTOM","hits":89,"comments":7,"url":"http://m.ruliweb.com/community/board/300143/read/40670115","writeDt":1547168681000},{"order":122,"communityCode":"PPOMPPU","bbsId":"freeboard","articleNo":6234350,"title":"발암주의))양승태에게 힘내세요해대는 매국단쳌ㅋㅋㅋㅋㅋ","writerType":"T","writer":"캬뷰","hits":127,"comments":2,"url":"http://m.ppomppu.co.kr/new/bbs_view.php?id=freeboard&no=6234350","writeDt":1547168678000},{"order":123,"communityCode":"DDANZI","bbsId":"free","articleNo":544923056,"title":"오늘이 태어난지............","writerType":"T","writer":"기차타고","hits":56,"comments":2,"url":"http://www.ddanzi.com/free/544923056","writeDt":1547168662000},{"order":124,"communityCode":"RULIWEB","bbsId":"300143","articleNo":40670114,"title":"엘사 멘붕하는 만화.manga","writerType":"T","writer":"아마가미","hits":529,"comments":5,"url":"http://m.ruliweb.com/community/board/300143/read/40670114","writeDt":1547168659000},{"order":125,"communityCode":"DDANZI","bbsId":"free","articleNo":544923029,"title":"여성단체는 정신대 문제에 관심이 없다?","writerType":"T","writer":"채널.넘버5","hits":143,"comments":5,"url":"http://www.ddanzi.com/free/544923029","writeDt":1547168647000},{"order":126,"communityCode":"PPOMPPU","bbsId":"freeboard","articleNo":6234349,"title":"협력이익공유제와 공수처신설.","writerType":"T","writer":"마에종","hits":40,"comments":1,"url":"http://m.ppomppu.co.kr/new/bbs_view.php?id=freeboard&no=6234349","writeDt":1547168643000},{"order":127,"communityCode":"PPOMPPU","bbsId":"freeboard","articleNo":6234348,"title":"\"'신과함께3·4', 롯데→CJ 품에\"…CJ ENM, 김용화 감독 덱스터 인수","writerType":"I","writer":"http://nic.ppomppu.co.kr/zboard/nickcon/46637.gif?v=201901111009","hits":258,"comments":2,"url":"http://m.ppomppu.co.kr/new/bbs_view.php?id=freeboard&no=6234348","writeDt":1547168641000},{"order":128,"communityCode":"INVEN","bbsId":"2097","articleNo":1132935,"title":"핵폐기물 보관 장소","writerType":"T","writer":"퀸부끄","hits":312,"comments":4,"url":"http://m.inven.co.kr/board/powerbbs.php?come_idx=2097&l=1132935","writeDt":1547168640000},{"order":129,"communityCode":"FMKOREA","bbsId":"humor","articleNo":1513465095,"title":"아싸들한테 팩폭 날리는 여자아이돌.gif","writerType":"T","writer":"푸른바닷길","hits":204,"comments":0,"url":"https://m.fmkorea.com/1513465095","writeDt":1547168640000},{"order":130,"communityCode":"FMKOREA","bbsId":"humor","articleNo":1513444904,"title":"우리나라 식재료가 비싼 이유 중 하나","writerType":"T","writer":"호벤투스","hits":223,"comments":12,"url":"https://m.fmkorea.com/1513444904","writeDt":1547168640000},{"order":131,"communityCode":"FMKOREA","bbsId":"humor","articleNo":1513464745,"title":"블랙넛 징역 6개월, 집행유예 2년 ㅋㅋㅋㅋ","writerType":"T","writer":"아름다운세상","hits":382,"comments":4,"url":"https://m.fmkorea.com/1513464745","writeDt":1547168640000},{"order":132,"communityCode":"MLBPARK","bbsId":"bullpen","articleNo":201901110026950124,"title":"2000년 초까지 이견없는 100% 창원 만남의 장소","writerType":"T","writer":"Wallflower","hits":152,"comments":3,"url":"http://mlbpark.donga.com/mp/b.php?p=1&b=bullpen&id=201901110026950124&site=donga.com","writeDt":1547168640000},{"order":133,"communityCode":"MLBPARK","bbsId":"bullpen","articleNo":201901110026950127,"title":"유튜버 제일 잘나가는 상황극 인싸들이","writerType":"T","writer":"그패봐봐","hits":294,"comments":2,"url":"http://mlbpark.donga.com/mp/b.php?p=1&b=bullpen&id=201901110026950127&site=donga.com","writeDt":1547168640000},{"order":134,"communityCode":"MLBPARK","bbsId":"bullpen","articleNo":201901110026950130,"title":"솔직히 김보름이 노선영 왕따시켰다는건 여자사회 좀만 알면 말도 안되는거 알수 있죠.","writerType":"T","writer":"아이주아리","hits":283,"comments":3,"url":"http://mlbpark.donga.com/mp/b.php?p=1&b=bullpen&id=201901110026950130&site=donga.com","writeDt":1547168640000},{"order":135,"communityCode":"MLBPARK","bbsId":"bullpen","articleNo":201901110026950133,"title":"대구 살면서 한번도 안 가본 영화관.jpg","writerType":"T","writer":"십자인대","hits":470,"comments":13,"url":"http://mlbpark.donga.com/mp/b.php?p=1&b=bullpen&id=201901110026950133&site=donga.com","writeDt":1547168640000},{"order":136,"communityCode":"BOBAEDREAM","bbsId":"freeb","articleNo":1552106,"title":"부가세땜시 바뿌네요 ㅠㅠ","writerType":"T","writer":"40살","hits":57,"comments":8,"url":"http://m.bobaedream.co.kr/board/bbs_view/freeb/1552106","writeDt":1547168640000},{"order":137,"communityCode":"BOBAEDREAM","bbsId":"strange","articleNo":2732067,"title":"우유 먹으면 설사해서 안먹는다는 분들..","writerType":"T","writer":"이미사정중입니..","hits":722,"comments":6,"url":"http://m.bobaedream.co.kr/board/bbs_view/strange/2732067","writeDt":1547168640000},{"order":138,"communityCode":"CLIEN","bbsId":"park","articleNo":13040158,"title":"어제 눈알에 관련된 새욕을 배웠어요","writerType":"T","writer":"콩소어","hits":378,"comments":2,"url":"https://m.clien.net/service/board/park/13040158","writeDt":1547168634000},{"order":139,"communityCode":"RULIWEB","bbsId":"300143","articleNo":40670111,"title":"(더러움 주의)아니","writerType":"T","writer":"LEE나다","hits":88,"comments":3,"url":"http://m.ruliweb.com/community/board/300143/read/40670111","writeDt":1547168631000},{"order":140,"communityCode":"RULIWEB","bbsId":"300143","articleNo":40670110,"title":"PC에도 블루투스 기능 추가하려면 동글 사다 끼우면 됨?","writerType":"T","writer":"l83kd7qk","hits":69,"comments":5,"url":"http://m.ruliweb.com/community/board/300143/read/40670110","writeDt":1547168625000},{"order":141,"communityCode":"RULIWEB","bbsId":"300143","articleNo":40670109,"title":"우중이가 요새 그러는건","writerType":"T","writer":"PPAPP","hits":54,"comments":3,"url":"http://m.ruliweb.com/community/board/300143/read/40670109","writeDt":1547168624000},{"order":142,"communityCode":"SLRCLUB","bbsId":"free","articleNo":36850936,"title":"나 최하 빈민 소외계층 조식","writerType":"T","writer":"RE-ULTRA.PHOTO","hits":277,"comments":10,"url":"http://m.slrclub.com/v/free/36850936","writeDt":1547168614000},{"order":143,"communityCode":"RULIWEB","bbsId":"300143","articleNo":40670108,"title":"[@] 아이코 산책카메라 밈","writerType":"T","writer":"우렝전사남캐","hits":121,"comments":1,"url":"http://m.ruliweb.com/community/board/300143/read/40670108","writeDt":1547168611000},{"order":144,"communityCode":"RULIWEB","bbsId":"300143","articleNo":40670107,"title":"[신데마스] 여우같은 마누라와 토끼같은 자식","writerType":"T","writer":"루리웹-3521363541","hits":203,"comments":7,"url":"http://m.ruliweb.com/community/board/300143/read/40670107","writeDt":1547168609000},{"order":145,"communityCode":"RULIWEB","bbsId":"300143","articleNo":40670106,"title":"남북유게 분리시기 유게 근황","writerType":"T","writer":"나오","hits":217,"comments":8,"url":"http://m.ruliweb.com/community/board/300143/read/40670106","writeDt":1547168601000},{"order":146,"communityCode":"SLRCLUB","bbsId":"free","articleNo":36850935,"title":"요번주 pd 수첩 이후 황창규에 대한 기사","writerType":"T","writer":"블랙카나리","hits":177,"comments":2,"url":"http://m.slrclub.com/v/free/36850935","writeDt":1547168601000},{"order":147,"communityCode":"SLRCLUB","bbsId":"free","articleNo":36850934,"title":"4년된 fhd 티비에서 LG 4k티비로 바꾼 소감","writerType":"T","writer":"블러드본","hits":107,"comments":0,"url":"http://m.slrclub.com/v/free/36850934","writeDt":1547168599000},{"order":148,"communityCode":"RULIWEB","bbsId":"300143","articleNo":40670105,"title":"페소나 확장판 어느 정도임?","writerType":"T","writer":"4 river","hits":92,"comments":7,"url":"http://m.ruliweb.com/community/board/300143/read/40670105","writeDt":1547168595000},{"order":149,"communityCode":"RULIWEB","bbsId":"300143","articleNo":40670104,"title":"어린 시절 합법 쩡.jpg","writerType":"T","writer":"행운의 블랙기업","hits":453,"comments":3,"url":"http://m.ruliweb.com/community/board/300143/read/40670104","writeDt":1547168594000},{"order":150,"communityCode":"RULIWEB","bbsId":"300143","articleNo":40670103,"title":"블리자드오피셜) 일리단은 사실 말퓨리온을 내심","writerType":"T","writer":"Geniustudy","hits":291,"comments":5,"url":"http://m.ruliweb.com/community/board/300143/read/40670103","writeDt":1547168591000},{"order":151,"communityCode":"SLRCLUB","bbsId":"free","articleNo":36850933,"title":"아이패드 프로 2세대에서 3세대로 가면 확 좋나요??","writerType":"T","writer":"아라리가났네","hits":39,"comments":2,"url":"http://m.slrclub.com/v/free/36850933","writeDt":1547168588000},{"order":152,"communityCode":"RULIWEB","bbsId":"300143","articleNo":40670102,"title":"페그오만화","writerType":"T","writer":"스섹","hits":215,"comments":1,"url":"http://m.ruliweb.com/community/board/300143/read/40670102","writeDt":1547168587000},{"order":153,"communityCode":"RULIWEB","bbsId":"300143","articleNo":40670101,"title":"나찌녀.jpg","writerType":"T","writer":"아마가미","hits":304,"comments":4,"url":"http://m.ruliweb.com/community/board/300143/read/40670101","writeDt":1547168583000},{"order":154,"communityCode":"PPOMPPU","bbsId":"freeboard","articleNo":6234347,"title":"옥션 CGV 티켓 성공","writerType":"T","writer":"spongebob99","hits":278,"comments":6,"url":"http://m.ppomppu.co.kr/new/bbs_view.php?id=freeboard&no=6234347","writeDt":1547168582000},{"order":155,"communityCode":"DVDPRIME","bbsId":"comm","articleNo":19678776,"title":"기자는 예의가 없어도 된다라....","writerType":"T","writer":"귀떽군","hits":239,"comments":3,"url":"https://dvdprime.com/g2/bbs/board.php?bo_table=comm&wr_id=19678776","writeDt":1547168581000},{"order":156,"communityCode":"FMKOREA","bbsId":"humor","articleNo":1513463825,"title":"인간이 너무 잔혹하다고 생각하는 게","writerType":"T","writer":"4위는너의거짓말","hits":252,"comments":2,"url":"https://m.fmkorea.com/1513463825","writeDt":1547168580000},{"order":157,"communityCode":"MLBPARK","bbsId":"bullpen","articleNo":201901110026950103,"title":"김보름으로 심석희 사태가 어떻게 묻힙니까?","writerType":"T","writer":"우배","hits":178,"comments":5,"url":"http://mlbpark.donga.com/mp/b.php?p=1&b=bullpen&id=201901110026950103&site=donga.com","writeDt":1547168580000},{"order":158,"communityCode":"MLBPARK","bbsId":"bullpen","articleNo":201901110026950106,"title":"우정사진.jpg","writerType":"T","writer":"ITsky","hits":670,"comments":6,"url":"http://mlbpark.donga.com/mp/b.php?p=1&b=bullpen&id=201901110026950106&site=donga.com","writeDt":1547168580000},{"order":159,"communityCode":"MLBPARK","bbsId":"bullpen","articleNo":201901110026950109,"title":"유튜버는 아무나 한게 아니라는 걸 배웠습니다.","writerType":"T","writer":"누렁이","hits":454,"comments":4,"url":"http://mlbpark.donga.com/mp/b.php?p=1&b=bullpen&id=201901110026950109&site=donga.com","writeDt":1547168580000},{"order":160,"communityCode":"MLBPARK","bbsId":"bullpen","articleNo":201901110026950112,"title":"불페너 만남의 장소.jpg","writerType":"T","writer":"신장의욕망","hits":320,"comments":2,"url":"http://mlbpark.donga.com/mp/b.php?p=1&b=bullpen&id=201901110026950112&site=donga.com","writeDt":1547168580000},{"order":161,"communityCode":"MLBPARK","bbsId":"bullpen","articleNo":201901110026950115,"title":"아재들은 공감하는 대학로 약속 장소.jpg","writerType":"T","writer":"KarlBoehm","hits":395,"comments":10,"url":"http://mlbpark.donga.com/mp/b.php?p=1&b=bullpen&id=201901110026950115&site=donga.com","writeDt":1547168580000},{"order":162,"communityCode":"MLBPARK","bbsId":"bullpen","articleNo":201901110026950118,"title":"홍대 앞 만남의 광장은 2군데로 나뉘던 걸로","writerType":"T","writer":"GrouchSmurf","hits":173,"comments":9,"url":"http://mlbpark.donga.com/mp/b.php?p=1&b=bullpen&id=201901110026950118&site=donga.com","writeDt":1547168580000},{"order":163,"communityCode":"MLBPARK","bbsId":"bullpen","articleNo":201901110026950121,"title":"전남 여수분들만 아는 만남의 장소.jpg","writerType":"T","writer":"LG만29년째","hits":454,"comments":5,"url":"http://mlbpark.donga.com/mp/b.php?p=1&b=bullpen&id=201901110026950121&site=donga.com","writeDt":1547168580000},{"order":164,"communityCode":"BOBAEDREAM","bbsId":"strange","articleNo":2732066,"title":"여기 유게에 조직적으로 활동하는 빡사모 있는듯","writerType":"T","writer":"낚시가즈아","hits":209,"comments":13,"url":"http://m.bobaedream.co.kr/board/bbs_view/strange/2732066","writeDt":1547168580000},{"order":165,"communityCode":"RULIWEB","bbsId":"300143","articleNo":40670100,"title":"안드로이드 매출 순위 보니 베그 생각보다 순위가ㅜ낮네","writerType":"T","writer":"108638.","hits":61,"comments":1,"url":"http://m.ruliweb.com/community/board/300143/read/40670100","writeDt":1547168577000},{"order":166,"communityCode":"RULIWEB","bbsId":"300143","articleNo":40670099,"title":"붕괴3이 돈을 쓸어담는 이유라면...","writerType":"T","writer":"조호수","hits":89,"comments":2,"url":"http://m.ruliweb.com/community/board/300143/read/40670099","writeDt":1547168571000},{"order":167,"communityCode":"RULIWEB","bbsId":"300143","articleNo":40670098,"title":"유비소프트 만큼 그래도 직원복지 잘되는 회사도 별로 없다던데","writerType":"T","writer":"92년생흑마법사","hits":53,"comments":1,"url":"http://m.ruliweb.com/community/board/300143/read/40670098","writeDt":1547168570000},{"order":168,"communityCode":"CLIEN","bbsId":"park","articleNo":13040156,"title":"공랭 CPU 쿨러 덩치, 승부 받습니다!","writerType":"I","writer":"https://cdn.clien.net/web/api/file/F94/1086060/f69832b20dbf41f2986.gif?gif=true","hits":542,"comments":9,"url":"https://m.clien.net/service/board/park/13040156","writeDt":1547168567000},{"order":169,"communityCode":"RULIWEB","bbsId":"300143","articleNo":40670097,"title":"페그오 동인지 번역하면서 깨달았다","writerType":"T","writer":"프라먀","hits":66,"comments":1,"url":"http://m.ruliweb.com/community/board/300143/read/40670097","writeDt":1547168563000},{"order":170,"communityCode":"COOK82","bbsId":"15","articleNo":2701050,"title":"파인텍 노사 합의 '노조원 5명 업무 복귀, 공장 정상 가동'","writerType":"T","writer":"최선을다하기..","hits":44,"comments":1,"url":"http://www.82cook.com/entiz/read.php?bn=15&num=2701050","writeDt":1547168554000},{"order":171,"communityCode":"CLIEN","bbsId":"park","articleNo":13040155,"title":"'병원 사람들 조문도 오지 마라' 간호사 유서 남긴 채..","writerType":"T","writer":"스웩","hits":1046,"comments":9,"url":"https://m.clien.net/service/board/park/13040155","writeDt":1547168553000},{"order":172,"communityCode":"RULIWEB","bbsId":"300143","articleNo":40670096,"title":"밀리@) 메이드","writerType":"T","writer":"메컷메컷","hits":103,"comments":1,"url":"http://m.ruliweb.com/community/board/300143/read/40670096","writeDt":1547168550000},{"order":173,"communityCode":"CLIEN","bbsId":"park","articleNo":13040154,"title":"모두가 행복할수 있는 세상이 옳은가?","writerType":"T","writer":"제리아스","hits":154,"comments":6,"url":"https://m.clien.net/service/board/park/13040154","writeDt":1547168549000},{"order":174,"communityCode":"CLIEN","bbsId":"park","articleNo":13040151,"title":"겨울엔 초록이 그립고.jpg","writerType":"T","writer":"줏엉","hits":626,"comments":4,"url":"https://m.clien.net/service/board/park/13040151","writeDt":1547168525000},{"order":175,"communityCode":"DDANZI","bbsId":"free","articleNo":544922748,"title":"아내와의 대화.","writerType":"T","writer":"얌전☺","hits":559,"comments":13,"url":"http://www.ddanzi.com/free/544922748","writeDt":1547168522000},{"order":176,"communityCode":"INVEN","bbsId":"2097","articleNo":1132934,"title":"중국산 전기면도기","writerType":"T","writer":"나무부엉","hits":485,"comments":4,"url":"http://m.inven.co.kr/board/powerbbs.php?come_idx=2097&l=1132934","writeDt":1547168520000},{"order":177,"communityCode":"FMKOREA","bbsId":"humor","articleNo":1513460968,"title":"다시보는 해버지","writerType":"T","writer":"또경영","hits":203,"comments":0,"url":"https://m.fmkorea.com/1513460968","writeDt":1547168520000},{"order":178,"communityCode":"MLBPARK","bbsId":"bullpen","articleNo":201901110026950094,"title":"부산 만남의 장소.jpg","writerType":"T","writer":"투승타타","hits":478,"comments":6,"url":"http://mlbpark.donga.com/mp/b.php?p=1&b=bullpen&id=201901110026950094&site=donga.com","writeDt":1547168520000},{"order":179,"communityCode":"MLBPARK","bbsId":"bullpen","articleNo":201901110026950100,"title":"이준석이 2019년 목표가 워마드 폐쇄라고 했나요?","writerType":"T","writer":"liveones","hits":123,"comments":6,"url":"http://mlbpark.donga.com/mp/b.php?p=1&b=bullpen&id=201901110026950100&site=donga.com","writeDt":1547168520000},{"order":180,"communityCode":"BOBAEDREAM","bbsId":"freeb","articleNo":1552104,"title":"부끄럽지만 저도 질문좀할께요","writerType":"T","writer":"난착한사람","hits":40,"comments":6,"url":"http://m.bobaedream.co.kr/board/bbs_view/freeb/1552104","writeDt":1547168520000},{"order":181,"communityCode":"BOBAEDREAM","bbsId":"freeb","articleNo":1552105,"title":"[수입중고] 티구안 VS 컴패스","writerType":"T","writer":"jh0116","hits":37,"comments":4,"url":"http://m.bobaedream.co.kr/board/bbs_view/freeb/1552105","writeDt":1547168520000},{"order":182,"communityCode":"BOBAEDREAM","bbsId":"strange","articleNo":2732065,"title":"도와주세요...","writerType":"T","writer":"정점의끝","hits":574,"comments":4,"url":"http://m.bobaedream.co.kr/board/bbs_view/strange/2732065","writeDt":1547168520000},{"order":183,"communityCode":"DDANZI","bbsId":"free","articleNo":544922766,"title":"면접 본거 파이였다","writerType":"T","writer":"로드마리🐈🍴🔪⭐","hits":271,"comments":13,"url":"http://www.ddanzi.com/free/544922766","writeDt":1547168515000},{"order":184,"communityCode":"PPOMPPU","bbsId":"freeboard","articleNo":6234346,"title":"디스커버리는 왜 인기가 있는지","writerType":"T","writer":"syoko쵸코","hits":678,"comments":18,"url":"http://m.ppomppu.co.kr/new/bbs_view.php?id=freeboard&no=6234346","writeDt":1547168515000},{"order":185,"communityCode":"SLRCLUB","bbsId":"free","articleNo":36850932,"title":"제가 그려본 가족 만환데 어떤가요? ㅋㅋㅋ","writerType":"T","writer":"행남","hits":203,"comments":3,"url":"http://m.slrclub.com/v/free/36850932","writeDt":1547168515000},{"order":186,"communityCode":"RULIWEB","bbsId":"300143","articleNo":40670094,"title":"재용TV 미국 버전","writerType":"T","writer":"초저녁 방랑자","hits":473,"comments":3,"url":"http://m.ruliweb.com/community/board/300143/read/40670094","writeDt":1547168510000},{"order":187,"communityCode":"RULIWEB","bbsId":"300143","articleNo":40670093,"title":"사람이 아니다.jpg","writerType":"T","writer":"아마가미","hits":345,"comments":7,"url":"http://m.ruliweb.com/community/board/300143/read/40670093","writeDt":1547168509000},{"order":188,"communityCode":"SLRCLUB","bbsId":"free","articleNo":36850931,"title":"롤스로이스가 크긴크군요..ㄷㄷㄷ","writerType":"T","writer":"Lv7.TurboS","hits":404,"comments":12,"url":"http://m.slrclub.com/v/free/36850931","writeDt":1547168507000},{"order":189,"communityCode":"DVDPRIME","bbsId":"comm","articleNo":19678770,"title":"하만카든 사설 수리업체 없을까요","writerType":"T","writer":"노브레인","hits":40,"comments":0,"url":"https://dvdprime.com/g2/bbs/board.php?bo_table=comm&wr_id=19678770","writeDt":1547168507000},{"order":190,"communityCode":"RULIWEB","bbsId":"300143","articleNo":40670092,"title":"여자들이 잘 안 지키는 약속","writerType":"T","writer":"rouga0","hits":162,"comments":2,"url":"http://m.ruliweb.com/community/board/300143/read/40670092","writeDt":1547168501000},{"order":191,"communityCode":"PPOMPPU","bbsId":"freeboard","articleNo":6234345,"title":"아침부터 불법주차 정말 짜증나네요..","writerType":"T","writer":"샤씨","hits":461,"comments":7,"url":"http://m.ppomppu.co.kr/new/bbs_view.php?id=freeboard&no=6234345","writeDt":1547168499000},{"order":192,"communityCode":"PPOMPPU","bbsId":"freeboard","articleNo":6234343,"title":"트럼프 : 민주당보다 중국이 더 쉽다..","writerType":"T","writer":"pm주딩이","hits":203,"comments":0,"url":"http://m.ppomppu.co.kr/new/bbs_view.php?id=freeboard&no=6234343","writeDt":1547168487000},{"order":193,"communityCode":"PPOMPPU","bbsId":"freeboard","articleNo":6234342,"title":"김어준의 생각 \"(김예령) 질문이 아니라 시비와 멱살잡이였다.","writerType":"T","writer":"총선승리","hits":172,"comments":1,"url":"http://m.ppomppu.co.kr/new/bbs_view.php?id=freeboard&no=6234342","writeDt":1547168485000},{"order":194,"communityCode":"RULIWEB","bbsId":"300143","articleNo":40670091,"title":"러브코미디 하렘물 폭발하는거 보면 러브히나가 참 잘만들었어","writerType":"T","writer":"애플잭","hits":103,"comments":3,"url":"http://m.ruliweb.com/community/board/300143/read/40670091","writeDt":1547168482000},{"order":195,"communityCode":"RULIWEB","bbsId":"300143","articleNo":40670089,"title":"[아이마스]점심 시간의 마코토","writerType":"T","writer":"l스페이드l","hits":105,"comments":2,"url":"http://m.ruliweb.com/community/board/300143/read/40670089","writeDt":1547168477000},{"order":196,"communityCode":"PPOMPPU","bbsId":"freeboard","articleNo":6234341,"title":"옥션 cgv 저는 성공입니다.","writerType":"I","writer":"http://nic.ppomppu.co.kr/zboard/nickcon/100857.gif?v=201901111009","hits":256,"comments":4,"url":"http://m.ppomppu.co.kr/new/bbs_view.php?id=freeboard&no=6234341","writeDt":1547168475000},{"order":197,"communityCode":"DDANZI","bbsId":"free","articleNo":544922653,"title":"\"야권, 보수세력\" 이런 단어를 잘못쓰는 언론사..","writerType":"T","writer":"s(-_-)a","hits":137,"comments":0,"url":"http://www.ddanzi.com/free/544922653","writeDt":1547168468000},{"order":198,"communityCode":"CLIEN","bbsId":"park","articleNo":13040148,"title":"황푸강 넘으면서 드는 생각","writerType":"T","writer":"상하이변태","hits":182,"comments":1,"url":"https://m.clien.net/service/board/park/13040148","writeDt":1547168464000},{"order":199,"communityCode":"RULIWEB","bbsId":"300143","articleNo":40670088,"title":"[소녀전선] 우중 : 저에게도 휴식이 필요해요","writerType":"T","writer":"이사령","hits":235,"comments":5,"url":"http://m.ruliweb.com/community/board/300143/read/40670088","writeDt":1547168461000},{"order":200,"communityCode":"FMKOREA","bbsId":"humor","articleNo":1513452177,"title":"이수역 폭행) 개빡친 세계일보.jpg","writerType":"T","writer":"얍얍오오예얍얍","hits":344,"comments":2,"url":"https://m.fmkorea.com/1513452177","writeDt":1547168460000},{"order":201,"communityCode":"MLBPARK","bbsId":"bullpen","articleNo":201901110026950058,"title":"중국산 홍미노트6 사서 한국 알뜰폰 유심 그냥 꼽아서 사용 가능한가요?","writerType":"T","writer":"가르치고파라","hits":170,"comments":2,"url":"http://mlbpark.donga.com/mp/b.php?p=1&b=bullpen&id=201901110026950058&site=donga.com","writeDt":1547168460000},{"order":202,"communityCode":"MLBPARK","bbsId":"bullpen","articleNo":201901110026950061,"title":"몸매 위 아래 jpg","writerType":"T","writer":"B.Wayne","hits":1148,"comments":12,"url":"http://mlbpark.donga.com/mp/b.php?p=1&b=bullpen&id=201901110026950061&site=donga.com","writeDt":1547168460000},{"order":203,"communityCode":"MLBPARK","bbsId":"bullpen","articleNo":201901110026950067,"title":"대구 만남의 장소 이견없는 원탑","writerType":"T","writer":"엔팍","hits":507,"comments":24,"url":"http://mlbpark.donga.com/mp/b.php?p=1&b=bullpen&id=201901110026950067&site=donga.com","writeDt":1547168460000},{"order":204,"communityCode":"MLBPARK","bbsId":"bullpen","articleNo":201901110026950070,"title":"호불호 많이 갈리는 음식 갑.jpg","writerType":"T","writer":"九州物語","hits":343,"comments":4,"url":"http://mlbpark.donga.com/mp/b.php?p=1&b=bullpen&id=201901110026950070&site=donga.com","writeDt":1547168460000},{"order":205,"communityCode":"MLBPARK","bbsId":"bullpen","articleNo":201901110026950073,"title":"잠실은 8번출구에서 만나서 로또 한 장 사고 시작하죠","writerType":"T","writer":"한티","hits":175,"comments":5,"url":"http://mlbpark.donga.com/mp/b.php?p=1&b=bullpen&id=201901110026950073&site=donga.com","writeDt":1547168460000},{"order":206,"communityCode":"MLBPARK","bbsId":"bullpen","articleNo":201901110026950076,"title":"세종의 식습관.jpg","writerType":"T","writer":"호금전","hits":1151,"comments":10,"url":"http://mlbpark.donga.com/mp/b.php?p=1&b=bullpen&id=201901110026950076&site=donga.com","writeDt":1547168460000},{"order":207,"communityCode":"MLBPARK","bbsId":"bullpen","articleNo":201901110026950079,"title":"김보름 건은 진짜 소름이네요","writerType":"T","writer":"서율엘지","hits":830,"comments":10,"url":"http://mlbpark.donga.com/mp/b.php?p=1&b=bullpen&id=201901110026950079&site=donga.com","writeDt":1547168460000},{"order":208,"communityCode":"MLBPARK","bbsId":"bullpen","articleNo":201901110026950082,"title":"일본갈때마다 놀라는건 하늘이 너무 맑아서 놀람...","writerType":"T","writer":"이글스홈런","hits":356,"comments":8,"url":"http://mlbpark.donga.com/mp/b.php?p=1&b=bullpen&id=201901110026950082&site=donga.com","writeDt":1547168460000},{"order":209,"communityCode":"MLBPARK","bbsId":"bullpen","articleNo":201901110026950085,"title":"부산 대표적 만남의 장소들","writerType":"T","writer":"윌리안","hits":314,"comments":8,"url":"http://mlbpark.donga.com/mp/b.php?p=1&b=bullpen&id=201901110026950085&site=donga.com","writeDt":1547168460000},{"order":210,"communityCode":"CLIEN","bbsId":"park","articleNo":13040146,"title":"이러해도 알집인가요...?","writerType":"I","writer":"https://cdn.clien.net/web/api/file/F94/6029626/13f6ac72fa5474.gif?gif=true","hits":935,"comments":12,"url":"https://m.clien.net/service/board/park/13040146","writeDt":1547168456000},{"order":211,"communityCode":"RULIWEB","bbsId":"300143","articleNo":40670087,"title":"거세를 하거나 게이여도 성추행으로 고소를 먹을까","writerType":"T","writer":"hmuagh","hits":145,"comments":6,"url":"http://m.ruliweb.com/community/board/300143/read/40670087","writeDt":1547168456000},{"order":212,"communityCode":"CLIEN","bbsId":"park","articleNo":13040145,"title":"아베 '다음엔 내가 김정은 만나야..여러 수단으로 의견교환 중'","writerType":"T","writer":"충전중yo","hits":337,"comments":1,"url":"https://m.clien.net/service/board/park/13040145","writeDt":1547168450000},{"order":213,"communityCode":"DDANZI","bbsId":"free","articleNo":544922563,"title":"먹방 꿈나무 ㅋㅋㅋ","writerType":"T","writer":"흉기알바","hits":259,"comments":0,"url":"http://www.ddanzi.com/free/544922563","writeDt":1547168449000},{"order":214,"communityCode":"HUMORUNIV","bbsId":"pdswait","articleNo":6636128,"title":"자고일어나니 2kg쪄있음","writerType":"T","writer":"카가네미렌","hits":101,"comments":8,"url":"http://m.humoruniv.com/board/read.html?table=pdswait&number=6636128","writeDt":1547168432000},{"order":215,"communityCode":"RULIWEB","bbsId":"300143","articleNo":40670086,"title":"(뉴베가스)빡대가리 배달부.manga","writerType":"T","writer":"아마가미","hits":512,"comments":6,"url":"http://m.ruliweb.com/community/board/300143/read/40670086","writeDt":1547168426000},{"order":216,"communityCode":"RULIWEB","bbsId":"300143","articleNo":40670085,"title":"금연하면서 살빼기 진짜 어렵다...","writerType":"T","writer":"lIllIl","hits":138,"comments":6,"url":"http://m.ruliweb.com/community/board/300143/read/40670085","writeDt":1547168422000},{"order":217,"communityCode":"DDANZI","bbsId":"free","articleNo":544922528,"title":"기레기에 분노하는 이유는","writerType":"T","writer":"이웃삼촌","hits":108,"comments":2,"url":"http://www.ddanzi.com/free/544922528","writeDt":1547168417000},{"order":218,"communityCode":"RULIWEB","bbsId":"300143","articleNo":40670084,"title":"먹이를 노리는 악어의 속도 gif","writerType":"T","writer":"거칠마루잉","hits":449,"comments":1,"url":"http://m.ruliweb.com/community/board/300143/read/40670084","writeDt":1547168417000},{"order":219,"communityCode":"PPOMPPU","bbsId":"freeboard","articleNo":6234340,"title":"유플 멤버쉽어플에서 허니바게트볼 무료 (선착순, 유플고객만 가능)","writerType":"I","writer":"http://nic.ppomppu.co.kr/zboard/nickcon/637510.gif?v=201901111009","hits":211,"comments":9,"url":"http://m.ppomppu.co.kr/new/bbs_view.php?id=freeboard&no=6234340","writeDt":1547168414000},{"order":220,"communityCode":"SLRCLUB","bbsId":"free","articleNo":36850929,"title":"신개념 길빵 담배충 논리..","writerType":"T","writer":"시그라프","hits":218,"comments":7,"url":"http://m.slrclub.com/v/free/36850929","writeDt":1547168408000},{"order":221,"communityCode":"DDANZI","bbsId":"free","articleNo":544922493,"title":"박주민 \"양승태의 회견, 법원 '공범'들에게 보내는 메시지\"","writerType":"T","writer":"ＴＷＩＣＥ","hits":373,"comments":2,"url":"http://www.ddanzi.com/free/544922493","writeDt":1547168407000},{"order":222,"communityCode":"CLIEN","bbsId":"park","articleNo":13040143,"title":"구글포토가 자동으로 사진을 만들어 주기도 하는군요.","writerType":"I","writer":"https://cdn.clien.net/web/api/file/F94/1089237/33dd2e6fddd0481abfc.gif?gif=true","hits":738,"comments":7,"url":"https://m.clien.net/service/board/park/13040143","writeDt":1547168403000},{"order":223,"communityCode":"INVEN","bbsId":"2097","articleNo":1132933,"title":"국회에 몰아치는 페미니즘 광풍..","writerType":"T","writer":"코우메","hits":474,"comments":5,"url":"http://m.inven.co.kr/board/powerbbs.php?come_idx=2097&l=1132933","writeDt":1547168400000},{"order":224,"communityCode":"FMKOREA","bbsId":"humor","articleNo":1513459055,"title":"아 변기 막혔는데 ㄹㅇ 빡치네","writerType":"T","writer":"톰클라스","hits":519,"comments":10,"url":"https://m.fmkorea.com/1513459055","writeDt":1547168400000},{"order":225,"communityCode":"MLBPARK","bbsId":"bullpen","articleNo":201901110026950046,"title":"서울 서부권 만남의 장소","writerType":"T","writer":"목사최태민","hits":348,"comments":6,"url":"http://mlbpark.donga.com/mp/b.php?p=1&b=bullpen&id=201901110026950046&site=donga.com","writeDt":1547168400000},{"order":226,"communityCode":"MLBPARK","bbsId":"bullpen","articleNo":201901110026950049,"title":"[아이즈원] 벤치즈 새로운 고화질.jpg","writerType":"T","writer":"콜로니아","hits":280,"comments":3,"url":"http://mlbpark.donga.com/mp/b.php?p=1&b=bullpen&id=201901110026950049&site=donga.com","writeDt":1547168400000},{"order":227,"communityCode":"MLBPARK","bbsId":"bullpen","articleNo":201901110026950052,"title":"공백기 동안의 연말 정산 관련 문의드립니다.","writerType":"T","writer":"jennys","hits":42,"comments":1,"url":"http://mlbpark.donga.com/mp/b.php?p=1&b=bullpen&id=201901110026950052&site=donga.com","writeDt":1547168400000},{"order":228,"communityCode":"MLBPARK","bbsId":"bullpen","articleNo":201901110026950055,"title":"문황폐하께 문후올립니다.","writerType":"T","writer":"파파이스","hits":94,"comments":1,"url":"http://mlbpark.donga.com/mp/b.php?p=1&b=bullpen&id=201901110026950055&site=donga.com","writeDt":1547168400000},{"order":229,"communityCode":"DDANZI","bbsId":"free","articleNo":544922322,"title":"와이프 노트북 사줄려는데 사양 좀 ㄷㄷㄷㄷㄷㄷㄷ","writerType":"T","writer":"[♩]고고씽","hits":311,"comments":18,"url":"http://www.ddanzi.com/free/544922322","writeDt":1547168392000},{"order":230,"communityCode":"RULIWEB","bbsId":"300143","articleNo":40670083,"title":"널리 쓰이는(쓰였던) 게 신기한 유행어들","writerType":"T","writer":"솔저: 76","hits":159,"comments":8,"url":"http://m.ruliweb.com/community/board/300143/read/40670083","writeDt":1547168390000},{"order":231,"communityCode":"CLIEN","bbsId":"park","articleNo":13040141,"title":"결국 언론이 쓰레깁니다.","writerType":"T","writer":"댓츠노노","hits":315,"comments":2,"url":"https://m.clien.net/service/board/park/13040141","writeDt":1547168385000},{"order":232,"communityCode":"RULIWEB","bbsId":"300143","articleNo":40670082,"title":"근데 장난아니라 던파 메이플보다 못한 rpg게임이 뭐이리 많아;","writerType":"T","writer":"뾰족머리삼돌이","hits":146,"comments":2,"url":"http://m.ruliweb.com/community/board/300143/read/40670082","writeDt":1547168378000},{"order":233,"communityCode":"RULIWEB","bbsId":"300143","articleNo":40670081,"title":"짤 달리다 철퇴먹어서 앞으로 짤은 안달리기로 했음","writerType":"T","writer":"다크갈비","hits":258,"comments":6,"url":"http://m.ruliweb.com/community/board/300143/read/40670081","writeDt":1547168369000},{"order":234,"communityCode":"HUMORUNIV","bbsId":"pdswait","articleNo":6636127,"title":"1월 11일을 꽃과 함께!","writerType":"T","writer":"플라워마에스트로","hits":30,"comments":4,"url":"http://m.humoruniv.com/board/read.html?table=pdswait&number=6636127","writeDt":1547168364000},{"order":235,"communityCode":"SLRCLUB","bbsId":"free","articleNo":36850928,"title":"외근 나가는데 신입여직원 때문에 짜증난썰 ㄷㄷㄷ","writerType":"T","writer":"㈜바나나안바나나","hits":297,"comments":23,"url":"http://m.slrclub.com/v/free/36850928","writeDt":1547168353000},{"order":236,"communityCode":"CLIEN","bbsId":"park","articleNo":13040139,"title":"대중교통을 많이 이용하다 보면..","writerType":"T","writer":"뎅뎅이!","hits":226,"comments":2,"url":"https://m.clien.net/service/board/park/13040139","writeDt":1547168347000},{"order":237,"communityCode":"FMKOREA","bbsId":"humor","articleNo":1513457619,"title":"타 커뮤니티에서 문제가 있는지 의견이 분분한 남자 부류.jpg","writerType":"T","writer":"푸른바닷길","hits":100,"comments":0,"url":"https://m.fmkorea.com/1513457619","writeDt":1547168340000},{"order":238,"communityCode":"MLBPARK","bbsId":"bullpen","articleNo":201901110026950031,"title":"다크소울은 쉬운편인가요?","writerType":"T","writer":"킹오파","hits":179,"comments":6,"url":"http://mlbpark.donga.com/mp/b.php?p=1&b=bullpen&id=201901110026950031&site=donga.com","writeDt":1547168340000},{"order":239,"communityCode":"MLBPARK","bbsId":"bullpen","articleNo":201901110026950034,"title":"떵개떵이라는 유튜버 300만 찍은 이유가 있네요","writerType":"T","writer":"그패봐봐","hits":799,"comments":11,"url":"http://mlbpark.donga.com/mp/b.php?p=1&b=bullpen&id=201901110026950034&site=donga.com","writeDt":1547168340000},{"order":240,"communityCode":"MLBPARK","bbsId":"bullpen","articleNo":201901110026950037,"title":"만남의 장소는..그냥 팡세 였는데...","writerType":"T","writer":"22현수22","hits":89,"comments":0,"url":"http://mlbpark.donga.com/mp/b.php?p=1&b=bullpen&id=201901110026950037&site=donga.com","writeDt":1547168340000},{"order":241,"communityCode":"MLBPARK","bbsId":"bullpen","articleNo":201901110026950043,"title":"성갈등이 진짜 심해졋다고 표면적으로 느끼는게","writerType":"T","writer":"불양","hits":237,"comments":0,"url":"http://mlbpark.donga.com/mp/b.php?p=1&b=bullpen&id=201901110026950043&site=donga.com","writeDt":1547168340000},{"order":242,"communityCode":"BOBAEDREAM","bbsId":"strange","articleNo":2732063,"title":"늑대 14마리가 일으킨 기적","writerType":"T","writer":"angka","hits":1119,"comments":3,"url":"http://m.bobaedream.co.kr/board/bbs_view/strange/2732063","writeDt":1547168340000},{"order":243,"communityCode":"RULIWEB","bbsId":"300143","articleNo":40670080,"title":"흔한 특촬 악역","writerType":"T","writer":"AtlacNcha","hits":601,"comments":5,"url":"http://m.ruliweb.com/community/board/300143/read/40670080","writeDt":1547168332000},{"order":244,"communityCode":"RULIWEB","bbsId":"300143","articleNo":40670079,"title":"킹핫산 이제 그랜드어쌔신 아니지 않음?","writerType":"T","writer":"루다","hits":149,"comments":3,"url":"http://m.ruliweb.com/community/board/300143/read/40670079","writeDt":1547168325000},{"order":245,"communityCode":"RULIWEB","bbsId":"300143","articleNo":40670078,"title":"사쿠라장 애니 덜팔릴수 밖에 없는게","writerType":"T","writer":"작은태양의 개미","hits":205,"comments":7,"url":"http://m.ruliweb.com/community/board/300143/read/40670078","writeDt":1547168323000},{"order":246,"communityCode":"RULIWEB","bbsId":"300143","articleNo":40670076,"title":"인종차별 때문에 퇴사했다는 블리자드 직원","writerType":"T","writer":"문셀오토마톤","hits":2515,"comments":10,"url":"http://m.ruliweb.com/community/board/300143/read/40670076","writeDt":1547168321000},{"order":247,"communityCode":"RULIWEB","bbsId":"300143","articleNo":40670077,"title":"아프리카 원주민들의 복장.gif","writerType":"T","writer":"뚫훍킹","hits":436,"comments":3,"url":"http://m.ruliweb.com/community/board/300143/read/40670077","writeDt":1547168321000},{"order":248,"communityCode":"HUMORUNIV","bbsId":"pdswait","articleNo":6636126,"title":"부장님이 방금 건네주고감ㅋ","writerType":"T","writer":"빠돌이남덕","hits":45,"comments":2,"url":"http://m.humoruniv.com/board/read.html?table=pdswait&number=6636126","writeDt":1547168319000},{"order":249,"communityCode":"RULIWEB","bbsId":"300143","articleNo":40670075,"title":"PC충 특유의 그림체는 왜 그런걸까?","writerType":"T","writer":"cthulhu","hits":176,"comments":9,"url":"http://m.ruliweb.com/community/board/300143/read/40670075","writeDt":1547168313000},{"order":250,"communityCode":"CLIEN","bbsId":"park","articleNo":13040138,"title":"오늘 네이버 아이디가 이상한 곳에서 접속을 했다고 뜨네요.","writerType":"T","writer":"Whitesand","hits":264,"comments":4,"url":"https://m.clien.net/service/board/park/13040138","writeDt":1547168308000},{"order":251,"communityCode":"RULIWEB","bbsId":"300143","articleNo":40670074,"title":"롯데리아가 날 또 배신했어..","writerType":"T","writer":"데드머니","hits":165,"comments":5,"url":"http://m.ruliweb.com/community/board/300143/read/40670074","writeDt":1547168306000},{"order":252,"communityCode":"PPOMPPU","bbsId":"freeboard","articleNo":6234339,"title":"김예령 기자 \"문 대통령을 걱정하는 마음으로 한 질문\"","writerType":"T","writer":"캬뷰","hits":635,"comments":16,"url":"http://m.ppomppu.co.kr/new/bbs_view.php?id=freeboard&no=6234339","writeDt":1547168305000},{"order":253,"communityCode":"HUMORUNIV","bbsId":"pdswait","articleNo":6636125,"title":"배달대행비 근황","writerType":"T","writer":"레고코리아","hits":36,"comments":4,"url":"http://m.humoruniv.com/board/read.html?table=pdswait&number=6636125","writeDt":1547168302000},{"order":254,"communityCode":"HUMORUNIV","bbsId":"pdswait","articleNo":6636124,"title":"어릴적 레고로 만들어본~","writerType":"T","writer":"판마님","hits":12,"comments":6,"url":"http://m.humoruniv.com/board/read.html?table=pdswait&number=6636124","writeDt":1547168284000},{"order":255,"communityCode":"INVEN","bbsId":"2097","articleNo":1132931,"title":"부모님이 80년대생인 아이돌","writerType":"T","writer":"퀸부끄","hits":82,"comments":0,"url":"http://m.inven.co.kr/board/powerbbs.php?come_idx=2097&l=1132931","writeDt":1547168280000},{"order":256,"communityCode":"INVEN","bbsId":"2097","articleNo":1132932,"title":"톨죽 그 이상의 병신","writerType":"T","writer":"읏큐","hits":527,"comments":12,"url":"http://m.inven.co.kr/board/powerbbs.php?come_idx=2097&l=1132932","writeDt":1547168280000},{"order":257,"communityCode":"MLBPARK","bbsId":"bullpen","articleNo":201901110026950010,"title":"미아삼거리 만남의 광장은 여기 아닐까요?","writerType":"T","writer":"tgif4395","hits":148,"comments":5,"url":"http://mlbpark.donga.com/mp/b.php?p=1&b=bullpen&id=201901110026950010&site=donga.com","writeDt":1547168280000},{"order":258,"communityCode":"MLBPARK","bbsId":"bullpen","articleNo":201901110026950013,"title":"이 가수 알면 빼박 아재 jpg","writerType":"T","writer":"B.Wayne","hits":651,"comments":7,"url":"http://mlbpark.donga.com/mp/b.php?p=1&b=bullpen&id=201901110026950013&site=donga.com","writeDt":1547168280000},{"order":259,"communityCode":"MLBPARK","bbsId":"bullpen","articleNo":201901110026950016,"title":"잠실에서 만날 때는 여기 앞에서 보자고 하면 되죠.jpg","writerType":"T","writer":"GrouchSmurf","hits":396,"comments":8,"url":"http://mlbpark.donga.com/mp/b.php?p=1&b=bullpen&id=201901110026950016&site=donga.com","writeDt":1547168280000},{"order":260,"communityCode":"MLBPARK","bbsId":"bullpen","articleNo":201901110026950019,"title":"1992 대통령배 남고부 결승전 휘문고 vs 부산중앙고","writerType":"T","writer":"두목포스","hits":83,"comments":1,"url":"http://mlbpark.donga.com/mp/b.php?p=1&b=bullpen&id=201901110026950019&site=donga.com","writeDt":1547168280000},{"order":261,"communityCode":"MLBPARK","bbsId":"bullpen","articleNo":201901110026950022,"title":"[KBL] 스윙맨 용병은 KBL에서 쉽지 않은 거 같네요","writerType":"T","writer":"용석주니어","hits":148,"comments":3,"url":"http://mlbpark.donga.com/mp/b.php?p=1&b=bullpen&id=201901110026950022&site=donga.com","writeDt":1547168280000},{"order":262,"communityCode":"MLBPARK","bbsId":"bullpen","articleNo":201901110026950025,"title":"현직 배달대행 기사(궁금한거 물어보세요)","writerType":"T","writer":"르로이사네","hits":281,"comments":9,"url":"http://mlbpark.donga.com/mp/b.php?p=1&b=bullpen&id=201901110026950025&site=donga.com","writeDt":1547168280000},{"order":263,"communityCode":"MLBPARK","bbsId":"bullpen","articleNo":201901110026950028,"title":"배텐 채팅방에서 김보름 얘기하면 강퇴당하겠죠?","writerType":"T","writer":"이안2016","hits":231,"comments":5,"url":"http://mlbpark.donga.com/mp/b.php?p=1&b=bullpen&id=201901110026950028&site=donga.com","writeDt":1547168280000},{"order":264,"communityCode":"RULIWEB","bbsId":"300143","articleNo":40670073,"title":"옛날 뉴스에는 성폭력 단어가 없어는데 ..","writerType":"T","writer":"1944에델바이스","hits":165,"comments":3,"url":"http://m.ruliweb.com/community/board/300143/read/40670073","writeDt":1547168273000},{"order":265,"communityCode":"RULIWEB","bbsId":"300143","articleNo":40670072,"title":"넥슨이 음악만큼은 진짜 잘뽑아낸다","writerType":"T","writer":"루리웹-3050241438","hits":115,"comments":2,"url":"http://m.ruliweb.com/community/board/300143/read/40670072","writeDt":1547168267000},{"order":266,"communityCode":"RULIWEB","bbsId":"300143","articleNo":40670071,"title":"컴퓨터 본체 하나 맞출려고 하는데 이정도면 평타치냐","writerType":"T","writer":"아서스 메네실","hits":248,"comments":19,"url":"http://m.ruliweb.com/community/board/300143/read/40670071","writeDt":1547168258000},{"order":267,"communityCode":"CLIEN","bbsId":"park","articleNo":13040135,"title":"lg롤러블TV과 삼성 모듈식 디스플레이","writerType":"T","writer":"헤르헤르","hits":680,"comments":6,"url":"https://m.clien.net/service/board/park/13040135","writeDt":1547168257000},{"order":268,"communityCode":"RULIWEB","bbsId":"300143","articleNo":40670070,"title":"교미의 계절이 도라와씁니다","writerType":"T","writer":"mih101820oy","hits":290,"comments":0,"url":"http://m.ruliweb.com/community/board/300143/read/40670070","writeDt":1547168256000},{"order":269,"communityCode":"DVDPRIME","bbsId":"comm","articleNo":19678749,"title":"오 여자친구 쇼케이스 V앱에서 라이브로 해주네요.","writerType":"T","writer":"프리즘_2","hits":52,"comments":0,"url":"https://dvdprime.com/g2/bbs/board.php?bo_table=comm&wr_id=19678749","writeDt":1547168255000},{"order":270,"communityCode":"DDANZI","bbsId":"free","articleNo":544922093,"title":"홍미노트 7 나왔네요","writerType":"T","writer":"함부로애틋하게~🎗","hits":425,"comments":17,"url":"http://www.ddanzi.com/free/544922093","writeDt":1547168249000},{"order":271,"communityCode":"CLIEN","bbsId":"park","articleNo":13040134,"title":"술집 알바가 느꼈다는 손님별 난이도.jpg","writerType":"I","writer":"https://cdn.clien.net/web/api/file/F94/1089347/c3645761a5964e06b8e.gif?gif=true","hits":2006,"comments":22,"url":"https://m.clien.net/service/board/park/13040134","writeDt":1547168248000},{"order":272,"communityCode":"CLIEN","bbsId":"park","articleNo":13040133,"title":"RGBW가 그렇게 별로인가요?","writerType":"T","writer":"박사뭐","hits":598,"comments":15,"url":"https://m.clien.net/service/board/park/13040133","writeDt":1547168245000},{"order":273,"communityCode":"RULIWEB","bbsId":"300143","articleNo":40670069,"title":"엑세스 플래시하는 유타를 보고 감탄하는 릿카","writerType":"T","writer":"l스페이드l","hits":131,"comments":1,"url":"http://m.ruliweb.com/community/board/300143/read/40670069","writeDt":1547168242000},{"order":274,"communityCode":"PPOMPPU","bbsId":"freeboard","articleNo":6234338,"title":"제주도 항공권 싸게 구할수 있을까요?","writerType":"T","writer":"socodlx","hits":245,"comments":15,"url":"http://m.ppomppu.co.kr/new/bbs_view.php?id=freeboard&no=6234338","writeDt":1547168238000},{"order":275,"communityCode":"RULIWEB","bbsId":"300143","articleNo":40670068,"title":"한그오 핫산이라는 거 몇시부터 뜸?","writerType":"T","writer":"Mig.","hits":46,"comments":5,"url":"http://m.ruliweb.com/community/board/300143/read/40670068","writeDt":1547168235000},{"order":276,"communityCode":"SLRCLUB","bbsId":"free","articleNo":36850927,"title":"맛있게 먹는 사발면 팁","writerType":"T","writer":"JS","hits":606,"comments":16,"url":"http://m.slrclub.com/v/free/36850927","writeDt":1547168229000},{"order":277,"communityCode":"DDANZI","bbsId":"free","articleNo":544921894,"title":"바하2 리메이크","writerType":"T","writer":"🍺볼빨다맞은춘자🐙","hits":307,"comments":3,"url":"http://www.ddanzi.com/free/544921894","writeDt":1547168226000},{"order":278,"communityCode":"CLIEN","bbsId":"park","articleNo":13040131,"title":"판사, 검사 선거제도 도입을 고려할 시점이 온듯 합니다.","writerType":"T","writer":"공묘","hits":360,"comments":9,"url":"https://m.clien.net/service/board/park/13040131","writeDt":1547168225000},{"order":279,"communityCode":"PPOMPPU","bbsId":"freeboard","articleNo":6234337,"title":"중국의 화웨이 구하기.jpg","writerType":"I","writer":"http://nic.ppomppu.co.kr/zboard/nickcon/1769680.gif?v=201901110958","hits":1480,"comments":25,"url":"http://m.ppomppu.co.kr/new/bbs_view.php?id=freeboard&no=6234337","writeDt":1547168224000},{"order":280,"communityCode":"DDANZI","bbsId":"free","articleNo":544922040,"title":"풀업과 친업의차이가뭐에요?(냉무)","writerType":"T","writer":"닉네임없음","hits":187,"comments":13,"url":"http://www.ddanzi.com/free/544922040","writeDt":1547168221000},{"order":281,"communityCode":"CLIEN","bbsId":"park","articleNo":13040130,"title":"노트북 호환 어댑터 샀습니다.","writerType":"T","writer":"빨간LED","hits":423,"comments":6,"url":"https://m.clien.net/service/board/park/13040130","writeDt":1547168220000},{"order":282,"communityCode":"MLBPARK","bbsId":"bullpen","articleNo":201901110026950001,"title":"\"김예령 기자, 나경원 민경욱 의원에겐 세상 다정한 트윗\" ㅎㅎㅎ","writerType":"T","writer":"나라사랑2","hits":921,"comments":16,"url":"http://mlbpark.donga.com/mp/b.php?p=1&b=bullpen&id=201901110026950001&site=donga.com","writeDt":1547168220000},{"order":283,"communityCode":"MLBPARK","bbsId":"bullpen","articleNo":201901110026950004,"title":"제가 여자랑 만났던 장소","writerType":"T","writer":"프로불페너","hits":574,"comments":4,"url":"http://mlbpark.donga.com/mp/b.php?p=1&b=bullpen&id=201901110026950004&site=donga.com","writeDt":1547168220000},{"order":284,"communityCode":"MLBPARK","bbsId":"bullpen","articleNo":201901110026950007,"title":"[아이즈원]브이앱  관장님 .GIF","writerType":"T","writer":"Drizzt","hits":350,"comments":4,"url":"http://mlbpark.donga.com/mp/b.php?p=1&b=bullpen&id=201901110026950007&site=donga.com","writeDt":1547168220000},{"order":285,"communityCode":"BOBAEDREAM","bbsId":"strange","articleNo":2732060,"title":"오지마.오지마...","writerType":"T","writer":"쌀케곳싸","hits":1030,"comments":0,"url":"http://m.bobaedream.co.kr/board/bbs_view/strange/2732060","writeDt":1547168220000},{"order":286,"communityCode":"BOBAEDREAM","bbsId":"strange","articleNo":2732061,"title":"본명 뺏긴 물건들","writerType":"T","writer":"승쨩","hits":1656,"comments":7,"url":"http://m.bobaedream.co.kr/board/bbs_view/strange/2732061","writeDt":1547168220000},{"order":287,"communityCode":"BOBAEDREAM","bbsId":"strange","articleNo":2732062,"title":"충격적인 돼지고기의 진실","writerType":"T","writer":"몬생긴똘똘이","hits":2090,"comments":9,"url":"http://m.bobaedream.co.kr/board/bbs_view/strange/2732062","writeDt":1547168220000},{"order":288,"communityCode":"RULIWEB","bbsId":"300143","articleNo":40670067,"title":"학교앞에서 사온 병아리가 죽은 썰.jpg","writerType":"T","writer":"귤벌레","hits":386,"comments":16,"url":"http://m.ruliweb.com/community/board/300143/read/40670067","writeDt":1547168214000},{"order":289,"communityCode":"RULIWEB","bbsId":"300143","articleNo":40670066,"title":"진짜 회사 말아먹은 애니메이션","writerType":"T","writer":"메이즈 폭렬시공","hits":366,"comments":9,"url":"http://m.ruliweb.com/community/board/300143/read/40670066","writeDt":1547168211000},{"order":290,"communityCode":"DDANZI","bbsId":"free","articleNo":544922006,"title":"어떤 시인이 한국 현재의 결혼에 대해 말한 것 중에","writerType":"T","writer":"HallelujahEssaim","hits":174,"comments":0,"url":"http://www.ddanzi.com/free/544922006","writeDt":1547168208000},{"order":291,"communityCode":"CLIEN","bbsId":"park","articleNo":13040129,"title":"김예령 기자가 같은 질문을 전, 전전 정권에 했으면","writerType":"T","writer":"Sunny78","hits":578,"comments":6,"url":"https://m.clien.net/service/board/park/13040129","writeDt":1547168204000},{"order":292,"communityCode":"RULIWEB","bbsId":"300143","articleNo":40670065,"title":"용사 바토리 보구 5랩 vs 무사시 명함","writerType":"T","writer":"루리웹-5675906698","hits":60,"comments":4,"url":"http://m.ruliweb.com/community/board/300143/read/40670065","writeDt":1547168201000},{"order":293,"communityCode":"RULIWEB","bbsId":"300143","articleNo":40670064,"title":"혐) 어떤 아동 애니에 대한 반응.jpg","writerType":"T","writer":"뇌속플래그빠진 녀석","hits":431,"comments":10,"url":"http://m.ruliweb.com/community/board/300143/read/40670064","writeDt":1547168198000},{"order":294,"communityCode":"DDANZI","bbsId":"free","articleNo":544921972,"title":"<질문> 노트북 추천 부탁드립니다","writerType":"T","writer":"흐흐72","hits":55,"comments":4,"url":"http://www.ddanzi.com/free/544921972","writeDt":1547168197000},{"order":295,"communityCode":"RULIWEB","bbsId":"300143","articleNo":40670063,"title":"새로 나온 과자 먹어봤는데","writerType":"T","writer":"깊은숲","hits":91,"comments":6,"url":"http://m.ruliweb.com/community/board/300143/read/40670063","writeDt":1547168196000},{"order":296,"communityCode":"PPOMPPU","bbsId":"freeboard","articleNo":6234336,"title":"흐 뽐게 육개장vs 미역국 뭐살까요","writerType":"T","writer":"피로엔웅담","hits":170,"comments":3,"url":"http://m.ppomppu.co.kr/new/bbs_view.php?id=freeboard&no=6234336","writeDt":1547168195000},{"order":297,"communityCode":"RULIWEB","bbsId":"300143","articleNo":40670062,"title":"광고가 만들어 지는 과정.jpg","writerType":"T","writer":"행운의 블랙기업","hits":184,"comments":2,"url":"http://m.ruliweb.com/community/board/300143/read/40670062","writeDt":1547168192000},{"order":298,"communityCode":"DDANZI","bbsId":"free","articleNo":544921830,"title":"문대통령이 아주 잘하고 있다는 증거","writerType":"T","writer":"📷메뉴얼포커스📷","hits":555,"comments":4,"url":"http://www.ddanzi.com/free/544921830","writeDt":1547168188000},{"order":299,"communityCode":"DDANZI","bbsId":"free","articleNo":544921958,"title":"혹시 레드비트즙 좋은데 파는데 아시는 분 있나유? ㄷㄷㄷ","writerType":"T","writer":"[-_ㅡ]암바치킨","hits":41,"comments":1,"url":"http://www.ddanzi.com/free/544921958","writeDt":1547168187000},{"order":300,"communityCode":"SLRCLUB","bbsId":"free","articleNo":36850926,"title":"4, 50대 아재들 추억 소환 -_-","writerType":"T","writer":"[AZE]공돌삼촌","hits":436,"comments":11,"url":"http://m.slrclub.com/v/free/36850926","writeDt":1547168180000}]}